{"assets":{"35BEB27BCFD2A0671D05F54DF7529643":{"type":"texture","index":16,"url":{"native":"assets\/13CFB201-949F-429C-BA8B-2140F9882998.pdf"},"width":1221,"height":1221},"B154F0DC13C3220DDA3B7C1CFDB4510A":{"type":"texture","index":0,"url":{"native":"assets\/13CFB201-949F-429C-BA8B-2140F9882998.pdf"},"width":1440,"height":810},"D371801AE33A0681B1EC4A22B0EBAF90":{"type":"texture","index":5,"url":{"native":"assets\/13CFB201-949F-429C-BA8B-2140F9882998.pdf"},"width":1076,"height":244},"765E2EA5592FB78B20F4EC16AC7FD7A0":{"type":"texture","index":8,"url":{"native":"assets\/13CFB201-949F-429C-BA8B-2140F9882998.pdf"},"width":1089,"height":171},"A5CB58C0EC26082A6A1D79A500ACD787":{"type":"texture","index":1,"url":{"native":"assets\/13CFB201-949F-429C-BA8B-2140F9882998.pdf"},"width":77,"height":22},"F1F1BD7DF227BF49CD6A9F7B48A28CFE":{"type":"texture","index":13,"url":{"native":"assets\/13CFB201-949F-429C-BA8B-2140F9882998.pdf"},"width":561,"height":34},"5925DF463A6EE8451015429E757C9BE9":{"type":"texture","index":6,"url":{"native":"assets\/13CFB201-949F-429C-BA8B-2140F9882998.pdf"},"width":656,"height":47},"713FBE56E9B67C4EE271793F37875EE2":{"type":"texture","index":11,"url":{"native":"assets\/13CFB201-949F-429C-BA8B-2140F9882998.pdf"},"width":72,"height":76},"4C0554448575FCE60EE0460D8D53B606":{"type":"texture","index":12,"url":{"native":"assets\/13CFB201-949F-429C-BA8B-2140F9882998.pdf"},"width":1031,"height":170},"1FA82269F68C3079E3607ACE6DA313F7":{"type":"texture","index":10,"url":{"native":"assets\/13CFB201-949F-429C-BA8B-2140F9882998.pdf"},"width":495,"height":72},"AD6454C95626FBA9C44ECC02468B867F":{"type":"texture","index":9,"url":{"native":"assets\/13CFB201-949F-429C-BA8B-2140F9882998.pdf"},"width":67,"height":67},"C1DFBD659D6C7908D9CDD0DC73CDF2C2":{"type":"texture","index":2,"url":{"native":"assets\/13CFB201-949F-429C-BA8B-2140F9882998.pdf"},"width":1071,"height":201},"99B08C3706E8C4B69AC19EB1564417ED":{"type":"texture","index":15,"url":{"native":"assets\/13CFB201-949F-429C-BA8B-2140F9882998.pdf"},"width":1079,"height":177},"5CF8AE5C26095294EC1BE0FB30046E9E":{"type":"texture","index":14,"url":{"native":"assets\/13CFB201-949F-429C-BA8B-2140F9882998.pdf"},"width":72,"height":76},"592D87926DE8EFDA616186EC5A2EF4D4":{"type":"texture","index":4,"url":{"native":"assets\/13CFB201-949F-429C-BA8B-2140F9882998.pdf"},"width":513,"height":47},"3ED2370E1D55959704E6F5A81484B4D9":{"type":"texture","index":7,"url":{"native":"assets\/13CFB201-949F-429C-BA8B-2140F9882998.pdf"},"width":594,"height":34},"7417B7E31B0B5A22D6C7FCE2448F6A8B":{"type":"texture","index":17,"url":{"native":"assets\/13CFB201-949F-429C-BA8B-2140F9882998.pdf"},"width":1759,"height":1769},"40E44A2A8C979B522C9F6AF8F9971FEB":{"type":"texture","index":3,"url":{"native":"assets\/13CFB201-949F-429C-BA8B-2140F9882998.pdf"},"width":501,"height":500}},"events":[{"effects":[{"beginTime":0,"baseLayer":{"animations":[],"initialState":{"affineTransform":[1,0,0,1,0,0],"masksToBounds":false,"rotation":0,"scale":1,"position":{"pointX":720,"pointY":405},"width":1440,"sublayerTransform":[1,0,0,0,0,1,0,0,0,0,1,0,0,0,0,1],"contentsRect":{"y":0,"x":0,"width":1,"height":1},"opacity":1,"edgeAntialiasingMask":251658240,"height":810,"hidden":false,"anchorPoint":{"pointX":0.5,"pointY":0.5}},"objectID":"0","layers":[{"animations":[],"initialState":{"affineTransform":[1,0,0,1,0,0],"masksToBounds":false,"rotation":0,"scale":1,"position":{"pointX":720,"pointY":405},"width":1440,"sublayerTransform":[1,0,0,0,0,1,0,0,0,0,1,-0.00046677216622367974,0,0,0,1],"contentsRect":{"y":0,"x":0,"width":1,"height":1},"opacity":1,"edgeAntialiasingMask":251658240,"height":810,"hidden":false,"anchorPoint":{"pointX":0.5,"pointY":0.5}},"layers":[{"animations":[],"initialState":{"affineTransform":[1,0,0,1,0,0],"masksToBounds":false,"rotation":0,"scale":1,"position":{"pointX":720,"pointY":405},"width":1440,"sublayerTransform":[1,0,0,0,0,1,0,0,0,0,1,0,0,0,0,1],"contentsRect":{"y":0,"x":0,"width":1,"height":1},"opacity":1,"edgeAntialiasingMask":251658240,"height":810,"hidden":false,"anchorPoint":{"pointX":0.5,"pointY":0.5}},"layers":[{"animations":[{"repeatCount":0,"removedOnCompletion":false,"from":{"scalar":false},"timingFunction":"EaseInEaseOut","additive":false,"timeOffset":0,"autoreverses":false,"property":"hidden","fillMode":"both","duration":3.75,"beginTime":0,"to":{"scalar":false}}],"layers":[],"texturedRectangle":{"isBackgroundTexture":true,"singleTextureOpacity":1,"textureType":1,"textBaseline":0,"textXHeight":0,"isVerticalText":false},"initialState":{"affineTransform":[1,0,0,1,0,0],"masksToBounds":false,"rotation":0,"scale":1,"position":{"pointX":720,"pointY":405},"width":1440,"sublayerTransform":[1,0,0,0,0,1,0,0,0,0,1,0,0,0,0,1],"contentsRect":{"y":0,"x":0,"width":1,"height":1},"opacity":1,"edgeAntialiasingMask":0,"height":810,"hidden":false,"anchorPoint":{"pointX":0.5,"pointY":0.5}},"texture":"B154F0DC13C3220DDA3B7C1CFDB4510A"}]},{"animations":[],"initialState":{"affineTransform":[1,0,0,1,0,0],"masksToBounds":false,"rotation":0,"scale":1,"position":{"pointX":720,"pointY":405},"width":1440,"sublayerTransform":[1,0,0,0,0,1,0,0,0,0,1,0,0,0,0,1],"contentsRect":{"y":0,"x":0,"width":1,"height":1},"opacity":1,"edgeAntialiasingMask":251658240,"height":810,"hidden":false,"anchorPoint":{"pointX":0.5,"pointY":0.5}},"layers":[{"animations":[{"repeatCount":0,"removedOnCompletion":false,"from":{"scalar":1},"timingFunction":"EaseInEaseOut","additive":false,"timeOffset":0,"autoreverses":false,"property":"opacity","fillMode":"both","duration":3.75,"beginTime":0,"to":{"scalar":0}}],"layers":[],"texturedRectangle":{"isBackgroundTexture":true,"singleTextureOpacity":1,"textureType":1,"textBaseline":0,"textXHeight":0,"isVerticalText":false},"initialState":{"affineTransform":[1,0,0,1,0,0],"masksToBounds":false,"rotation":0,"scale":1,"position":{"pointX":720,"pointY":405},"width":1440,"sublayerTransform":[1,0,0,0,0,1,0,0,0,0,1,0,0,0,0,1],"contentsRect":{"y":0,"x":0,"width":1,"height":1},"opacity":1,"edgeAntialiasingMask":0,"height":810,"hidden":false,"anchorPoint":{"pointX":0.5,"pointY":0.5}},"texture":"B154F0DC13C3220DDA3B7C1CFDB4510A"}]}]},{"animations":[],"initialState":{"affineTransform":[1,0,0,1,0,0],"masksToBounds":false,"rotation":0,"scale":1,"position":{"pointX":1323.021240234375,"pointY":82.690155029296875},"width":77,"sublayerTransform":[1,0,0,0,0,1,0,0,0,0,1,0,0,0,0,1],"contentsRect":{"y":0,"x":0,"width":1,"height":1},"opacity":1,"edgeAntialiasingMask":251658240,"height":22,"hidden":false,"anchorPoint":{"pointX":0.5,"pointY":0.5}},"layers":[{"animations":[],"initialState":{"affineTransform":[1,0,0,1,0,0],"masksToBounds":false,"rotation":0,"scale":1,"position":{"pointX":-564.521240234375,"pointY":333.30984497070312},"width":77,"sublayerTransform":[1,0,0,0,0,1,0,0,0,0,1,-0.00046677216622367974,0,0,0,1],"contentsRect":{"y":0,"x":0,"width":1,"height":1},"opacity":1,"edgeAntialiasingMask":251658240,"height":22,"hidden":false,"anchorPoint":{"pointX":-7.3314446783685066,"pointY":15.150447498668324}},"layers":[{"animations":[{"additive":false,"timeOffset":0,"beginTime":0,"repeatCount":0,"fillMode":"both","duration":3.75,"autoreverses":false,"animations":[{"repeatCount":0,"removedOnCompletion":true,"timingFunctions":[{"timingFunction":"custom","timingControlPoint1y":0.10000000149011612,"timingControlPoint2x":0.75,"timingControlPoint1x":0.25,"timingControlPoint2y":0.89999997615814209},{"timingFunction":"custom","timingControlPoint1y":0.10000000149011612,"timingControlPoint2x":0.75,"timingControlPoint1x":0.25,"timingControlPoint2y":0.89999997615814209}],"keyTimes":[0,0.29999999999999999,1],"additive":false,"values":[{"scalar":1},{"scalar":1.125},{"scalar":0}],"timeOffset":0,"autoreverses":false,"property":"transform.scale.xy","fillMode":"both","duration":1.875,"beginTime":0.025065104166666671},{"repeatCount":0,"removedOnCompletion":true,"from":{"scalar":1},"timingFunction":"EaseInEaseOut","additive":false,"timeOffset":0,"autoreverses":false,"property":"opacity","fillMode":"both","duration":1.875,"beginTime":0.025065104166666671,"to":{"scalar":0}},{"additive":false,"timeOffset":0,"beginTime":0,"from":{"scalar":false},"repeatCount":0,"fillMode":"both","duration":3.75,"autoreverses":false,"property":"hidden","to":{"scalar":false},"removedOnCompletion":true}],"removedOnCompletion":false}],"layers":[],"texturedRectangle":{"singleTextureOpacity":1,"textXHeight":0,"shapePath":{"lineWidth":1,"flatness":0.59999999999999998,"lineCapStyle":0,"elements":[{"type":"MoveToPoint","points":[[1.521240234375,1.690155029296875]]},{"type":"AddLine","points":[[75.999977111816406,1.690155029296875]]},{"type":"AddLine","points":[[75.999977111816406,20.309839248657227]]},{"type":"AddLine","points":[[1.521240234375,20.309839248657227]]},{"type":"AddLine","points":[[1.521240234375,1.690155029296875]]},{"type":"CloseSubpath"},{"type":"MoveToPoint","points":[[1.521240234375,1.690155029296875]]}],"windingRule":0,"lineJoinStyle":0,"miterLimit":10},"isBackgroundTexture":true,"textBaseline":0,"isVerticalText":false,"textureType":5},"initialState":{"affineTransform":[1,0,0,1,0,0],"masksToBounds":false,"rotation":0,"scale":1,"position":{"pointX":36.978759765625,"pointY":9.309844970703125},"width":77,"sublayerTransform":[1,0,0,0,0,1,0,0,0,0,1,0,0,0,0,1],"contentsRect":{"y":0,"x":0,"width":1,"height":1},"opacity":1,"edgeAntialiasingMask":0,"height":22,"hidden":false,"anchorPoint":{"pointX":0.5,"pointY":0.5}},"texture":"A5CB58C0EC26082A6A1D79A500ACD787"}]}]},{"animations":[],"initialState":{"affineTransform":[1,0,0,1,0,0],"masksToBounds":false,"rotation":0,"scale":1,"position":{"pointX":685.96623229980469,"pointY":528.06497192382812},"width":1071,"sublayerTransform":[1,0,0,0,0,1,0,0,0,0,1,0,0,0,0,1],"contentsRect":{"y":0,"x":0,"width":1,"height":1},"opacity":1,"edgeAntialiasingMask":251658240,"height":201,"hidden":false,"anchorPoint":{"pointX":0.5,"pointY":0.5}},"layers":[{"animations":[],"initialState":{"affineTransform":[1,0,0,1,0,0],"masksToBounds":false,"rotation":0,"scale":1,"position":{"pointX":569.53376770019531,"pointY":-22.564971923828125},"width":1071,"sublayerTransform":[1,0,0,0,0,1,0,0,0,0,1,-0.00046677216622367974,0,0,0,1],"contentsRect":{"y":0,"x":0,"width":1,"height":1},"opacity":1,"edgeAntialiasingMask":251658240,"height":201,"hidden":false,"anchorPoint":{"pointX":0.53177756087786676,"pointY":-0.11226354190959266}},"layers":[{"animations":[{"additive":false,"timeOffset":0,"beginTime":0,"repeatCount":0,"fillMode":"both","duration":3.75,"autoreverses":false,"animations":[{"repeatCount":0,"removedOnCompletion":true,"timingFunctions":[{"timingFunction":"custom","timingControlPoint1y":0.10000000149011612,"timingControlPoint2x":0.75,"timingControlPoint1x":0.25,"timingControlPoint2y":0.89999997615814209},{"timingFunction":"custom","timingControlPoint1y":0.10000000149011612,"timingControlPoint2x":0.75,"timingControlPoint1x":0.25,"timingControlPoint2y":0.89999997615814209}],"keyTimes":[0,0.29999999999999999,1],"additive":false,"values":[{"scalar":1},{"scalar":1.125},{"scalar":0}],"timeOffset":0,"autoreverses":false,"property":"transform.scale.xy","fillMode":"both","duration":1.875,"beginTime":0.3486328125},{"repeatCount":0,"removedOnCompletion":true,"from":{"scalar":1},"timingFunction":"EaseInEaseOut","additive":false,"timeOffset":0,"autoreverses":false,"property":"opacity","fillMode":"both","duration":1.875,"beginTime":0.3486328125,"to":{"scalar":0}},{"additive":false,"timeOffset":0,"beginTime":0,"from":{"scalar":false},"repeatCount":0,"fillMode":"both","duration":3.75,"autoreverses":false,"property":"hidden","to":{"scalar":false},"removedOnCompletion":true}],"removedOnCompletion":false}],"layers":[],"texturedRectangle":{"singleTextureOpacity":1,"textXHeight":0.072716417910447764,"textBaseline":0.9699749872459108,"isBackgroundTexture":true,"isVerticalText":false,"textColor":[0.098039217293262482,0.098039217293262482,0.098039217293262482,1],"textureType":6},"initialState":{"affineTransform":[1,0,0,1,0,0],"masksToBounds":false,"rotation":0,"scale":1,"position":{"pointX":535.03376770019531,"pointY":111.93502807617188},"width":1071,"sublayerTransform":[1,0,0,0,0,1,0,0,0,0,1,0,0,0,0,1],"contentsRect":{"y":0,"x":0,"width":1,"height":1},"opacity":1,"edgeAntialiasingMask":0,"height":201,"hidden":false,"anchorPoint":{"pointX":0.5,"pointY":0.5}},"texture":"C1DFBD659D6C7908D9CDD0DC73CDF2C2"}]}]},{"animations":[],"initialState":{"affineTransform":[1,0,0,1,0,0],"masksToBounds":false,"rotation":0,"scale":1,"position":{"pointX":1124.4106398261183,"pointY":829.18346697455559},"width":501,"sublayerTransform":[1,0,0,0,0,1,0,0,0,0,1,0,0,0,0,1],"contentsRect":{"y":0,"x":0,"width":1,"height":1},"opacity":1,"edgeAntialiasingMask":251658240,"height":500,"hidden":false,"anchorPoint":{"pointX":0.5,"pointY":0.5}},"layers":[{"animations":[],"initialState":{"affineTransform":[1,0,0,1,0,0],"masksToBounds":false,"rotation":0,"scale":1,"position":{"pointX":-153.91063982611831,"pointY":-174.18346697455559},"width":501,"sublayerTransform":[1,0,0,0,0,1,0,0,0,0,1,-0.00046677216622367974,0,0,0,1],"contentsRect":{"y":0,"x":0,"width":1,"height":1},"opacity":1,"edgeAntialiasingMask":251658240,"height":500,"hidden":false,"anchorPoint":{"pointX":-0.30720686592039581,"pointY":-0.34836693394911117}},"layers":[{"animations":[{"additive":false,"timeOffset":0,"beginTime":0,"repeatCount":0,"fillMode":"both","duration":3.75,"autoreverses":false,"animations":[{"repeatCount":0,"removedOnCompletion":true,"timingFunctions":[{"timingFunction":"custom","timingControlPoint1y":0.10000000149011612,"timingControlPoint2x":0.75,"timingControlPoint1x":0.25,"timingControlPoint2y":0.89999997615814209},{"timingFunction":"custom","timingControlPoint1y":0.10000000149011612,"timingControlPoint2x":0.75,"timingControlPoint1x":0.25,"timingControlPoint2y":0.89999997615814209}],"keyTimes":[0,0.29999999999999999,1],"additive":false,"values":[{"scalar":1},{"scalar":1.125},{"scalar":0}],"timeOffset":0,"autoreverses":false,"property":"transform.scale.xy","fillMode":"both","duration":1.875,"beginTime":0.1630859375},{"repeatCount":0,"removedOnCompletion":true,"from":{"scalar":1},"timingFunction":"EaseInEaseOut","additive":false,"timeOffset":0,"autoreverses":false,"property":"opacity","fillMode":"both","duration":1.875,"beginTime":0.1630859375,"to":{"scalar":0}},{"additive":false,"timeOffset":0,"beginTime":0,"from":{"scalar":false},"repeatCount":0,"fillMode":"both","duration":3.75,"autoreverses":false,"property":"hidden","to":{"scalar":false},"removedOnCompletion":true}],"removedOnCompletion":false}],"layers":[],"texturedRectangle":{"singleTextureOpacity":1,"textXHeight":0,"shapePath":{"lineWidth":1,"flatness":0.59999999999999998,"lineCapStyle":0,"elements":[{"type":"MoveToPoint","points":[[422.05015960665264,172.65592882730198]]},{"type":"AddCurve","points":[[379.41667100338304,77.954102276295089],[268.08492822987137,35.744574446327874],[173.38310167886448,78.378063049597472]]},{"type":"AddCurve","points":[[78.681261214011329,121.0115579166935],[36.471747297890488,232.34329442637886],[79.105235901160086,327.04512097738552]]},{"type":"AddCurve","points":[[121.73873076825612,421.74696144223878],[233.0704533640951,463.95648162218617],[327.77229382894825,421.32298675509014]]},{"type":"AddCurve","points":[[422.47412037995514,378.68949815182054],[464.6836544737489,267.35776929215513],[422.05015960665264,172.65592882730198]]},{"type":"CloseSubpath"},{"type":"MoveToPoint","points":[[422.05015960665264,172.65592882730198]]}],"windingRule":0,"lineJoinStyle":0,"miterLimit":10},"isBackgroundTexture":true,"textBaseline":0,"isVerticalText":false,"textureType":5},"initialState":{"affineTransform":[1,0,0,1,0,0],"masksToBounds":false,"rotation":0,"scale":1,"position":{"pointX":248.5893601738818,"pointY":248.81653302544441},"width":501,"sublayerTransform":[1,0,0,0,0,1,0,0,0,0,1,0,0,0,0,1],"contentsRect":{"y":0,"x":0,"width":1,"height":1},"opacity":1,"edgeAntialiasingMask":0,"height":500,"hidden":false,"anchorPoint":{"pointX":0.5,"pointY":0.5}},"texture":"40E44A2A8C979B522C9F6AF8F9971FEB"}]}]},{"animations":[],"initialState":{"affineTransform":[1,0,0,1,0,0],"masksToBounds":false,"rotation":0,"scale":1,"position":{"pointX":423.94480895996094,"pointY":90.823539733886719},"width":513,"sublayerTransform":[1,0,0,0,0,1,0,0,0,0,1,0,0,0,0,1],"contentsRect":{"y":0,"x":0,"width":1,"height":1},"opacity":1,"edgeAntialiasingMask":251658240,"height":47,"hidden":false,"anchorPoint":{"pointX":0.5,"pointY":0.5}},"layers":[{"animations":[],"initialState":{"affineTransform":[1,0,0,1,0,0],"masksToBounds":false,"rotation":0,"scale":1,"position":{"pointX":552.55519104003906,"pointY":337.67646026611328},"width":513,"sublayerTransform":[1,0,0,0,0,1,0,0,0,0,1,-0.00046677216622367974,0,0,0,1],"contentsRect":{"y":0,"x":0,"width":1,"height":1},"opacity":1,"edgeAntialiasingMask":251658240,"height":47,"hidden":false,"anchorPoint":{"pointX":1.0771056355556317,"pointY":7.1846055375768785}},"layers":[{"animations":[{"additive":false,"timeOffset":0,"beginTime":0,"repeatCount":0,"fillMode":"both","duration":3.75,"autoreverses":false,"animations":[{"repeatCount":0,"removedOnCompletion":true,"timingFunctions":[{"timingFunction":"custom","timingControlPoint1y":0.10000000149011612,"timingControlPoint2x":0.75,"timingControlPoint1x":0.25,"timingControlPoint2y":0.89999997615814209},{"timingFunction":"custom","timingControlPoint1y":0.10000000149011612,"timingControlPoint2x":0.75,"timingControlPoint1x":0.25,"timingControlPoint2y":0.89999997615814209}],"keyTimes":[0,0.29999999999999999,1],"additive":false,"values":[{"scalar":1},{"scalar":1.125},{"scalar":0}],"timeOffset":0,"autoreverses":false,"property":"transform.scale.xy","fillMode":"both","duration":1.875,"beginTime":0.1669921875},{"repeatCount":0,"removedOnCompletion":true,"from":{"scalar":1},"timingFunction":"EaseInEaseOut","additive":false,"timeOffset":0,"autoreverses":false,"property":"opacity","fillMode":"both","duration":1.875,"beginTime":0.1669921875,"to":{"scalar":0}},{"additive":false,"timeOffset":0,"beginTime":0,"from":{"scalar":false},"repeatCount":0,"fillMode":"both","duration":3.75,"autoreverses":false,"property":"hidden","to":{"scalar":false},"removedOnCompletion":true}],"removedOnCompletion":false}],"layers":[],"texturedRectangle":{"singleTextureOpacity":1,"textXHeight":0.67912765957446797,"textBaseline":0.93454341305063127,"isBackgroundTexture":true,"isVerticalText":false,"textColor":[0,0,0,1],"textureType":6},"initialState":{"affineTransform":[1,0,0,1,0,0],"masksToBounds":false,"rotation":0,"scale":1,"position":{"pointX":260.05519104003906,"pointY":25.176460266113281},"width":513,"sublayerTransform":[1,0,0,0,0,1,0,0,0,0,1,0,0,0,0,1],"contentsRect":{"y":0,"x":0,"width":1,"height":1},"opacity":1,"edgeAntialiasingMask":0,"height":47,"hidden":false,"anchorPoint":{"pointX":0.5,"pointY":0.5}},"texture":"592D87926DE8EFDA616186EC5A2EF4D4"}]}]},{"animations":[],"initialState":{"affineTransform":[1,0,0,1,0,0],"masksToBounds":false,"rotation":0,"scale":1,"position":{"pointX":694.57368469238281,"pointY":268.21676635742188},"width":1076,"sublayerTransform":[1,0,0,0,0,1,0,0,0,0,1,0,0,0,0,1],"contentsRect":{"y":0,"x":0,"width":1,"height":1},"opacity":1,"edgeAntialiasingMask":251658240,"height":244,"hidden":false,"anchorPoint":{"pointX":0.5,"pointY":0.5}},"layers":[{"animations":[],"initialState":{"affineTransform":[1,0,0,1,0,0],"masksToBounds":false,"rotation":0,"scale":1,"position":{"pointX":563.42631530761719,"pointY":258.78323364257812},"width":1076,"sublayerTransform":[1,0,0,0,0,1,0,0,0,0,1,-0.00046677216622367974,0,0,0,1],"contentsRect":{"y":0,"x":0,"width":1,"height":1},"opacity":1,"edgeAntialiasingMask":251658240,"height":244,"hidden":false,"anchorPoint":{"pointX":0.52363040456098253,"pointY":1.0605870231253203}},"layers":[{"animations":[{"additive":false,"timeOffset":0,"beginTime":0,"repeatCount":0,"fillMode":"both","duration":3.75,"autoreverses":false,"animations":[{"repeatCount":0,"removedOnCompletion":true,"timingFunctions":[{"timingFunction":"custom","timingControlPoint1y":0.10000000149011612,"timingControlPoint2x":0.75,"timingControlPoint1x":0.25,"timingControlPoint2y":0.89999997615814209},{"timingFunction":"custom","timingControlPoint1y":0.10000000149011612,"timingControlPoint2x":0.75,"timingControlPoint1x":0.25,"timingControlPoint2y":0.89999997615814209}],"keyTimes":[0,0.29999999999999999,1],"additive":false,"values":[{"scalar":1},{"scalar":1.125},{"scalar":0}],"timeOffset":0,"autoreverses":false,"property":"transform.scale.xy","fillMode":"both","duration":1.875,"beginTime":0.35026041666666669},{"repeatCount":0,"removedOnCompletion":true,"from":{"scalar":1},"timingFunction":"EaseInEaseOut","additive":false,"timeOffset":0,"autoreverses":false,"property":"opacity","fillMode":"both","duration":1.875,"beginTime":0.35026041666666669,"to":{"scalar":0}},{"additive":false,"timeOffset":0,"beginTime":0,"from":{"scalar":false},"repeatCount":0,"fillMode":"both","duration":3.75,"autoreverses":false,"property":"hidden","to":{"scalar":false},"removedOnCompletion":true}],"removedOnCompletion":false}],"layers":[],"texturedRectangle":{"singleTextureOpacity":1,"textXHeight":0.059901639344262292,"textBaseline":0.97383920848369598,"isBackgroundTexture":true,"isVerticalText":false,"textColor":[0.098039217293262482,0.098039217293262482,0.098039217293262482,1],"textureType":6},"initialState":{"affineTransform":[1,0,0,1,0,0],"masksToBounds":false,"rotation":0,"scale":1,"position":{"pointX":537.42631530761719,"pointY":133.78323364257812},"width":1076,"sublayerTransform":[1,0,0,0,0,1,0,0,0,0,1,0,0,0,0,1],"contentsRect":{"y":0,"x":0,"width":1,"height":1},"opacity":1,"edgeAntialiasingMask":0,"height":244,"hidden":false,"anchorPoint":{"pointX":0.5,"pointY":0.5}},"texture":"D371801AE33A0681B1EC4A22B0EBAF90"}]}]},{"animations":[],"initialState":{"affineTransform":[1,0,0,1,0,0],"masksToBounds":false,"rotation":0,"scale":1,"position":{"pointX":1323.021240234375,"pointY":82.690155029296875},"width":77,"sublayerTransform":[1,0,0,0,0,1,0,0,0,0,1,0,0,0,0,1],"contentsRect":{"y":0,"x":0,"width":1,"height":1},"opacity":1,"edgeAntialiasingMask":251658240,"height":22,"hidden":false,"anchorPoint":{"pointX":0.5,"pointY":0.5}},"layers":[{"animations":[{"additive":false,"timeOffset":0,"beginTime":0,"repeatCount":0,"fillMode":"both","duration":3.75,"autoreverses":false,"animations":[{"repeatCount":0,"removedOnCompletion":true,"timingFunctions":[{"timingFunction":"EaseIn"},{"timingFunction":"custom","timingControlPoint1y":0,"timingControlPoint2x":0.57624423503875732,"timingControlPoint1x":0,"timingControlPoint2y":1},{"timingFunction":"custom","timingControlPoint1y":0.10000000149011612,"timingControlPoint2x":1,"timingControlPoint1x":0.25,"timingControlPoint2y":1}],"keyTimes":[0,0.45000000000000001,0.66700000000000004,1],"additive":false,"values":[{"scalar":0},{"scalar":1.125},{"scalar":0.95199999999999996},{"scalar":1}],"timeOffset":0,"autoreverses":false,"property":"transform.scale.xy","fillMode":"both","duration":1.875,"beginTime":1.3300919532775879},{"repeatCount":0,"removedOnCompletion":true,"from":{"scalar":0},"timingFunction":"EaseInEaseOut","additive":false,"timeOffset":0,"autoreverses":false,"property":"opacity","fillMode":"both","duration":1.875,"beginTime":1.3300919532775879,"to":{"scalar":1}},{"additive":false,"timeOffset":0,"beginTime":0,"from":{"scalar":false},"repeatCount":0,"fillMode":"both","duration":3.75,"autoreverses":false,"property":"hidden","to":{"scalar":false},"removedOnCompletion":true}],"removedOnCompletion":false}],"layers":[],"texturedRectangle":{"singleTextureOpacity":1,"textXHeight":0,"shapePath":{"lineWidth":1,"flatness":0.59999999999999998,"lineCapStyle":0,"elements":[{"type":"MoveToPoint","points":[[1.521240234375,1.690155029296875]]},{"type":"AddLine","points":[[75.999977111816406,1.690155029296875]]},{"type":"AddLine","points":[[75.999977111816406,20.309839248657227]]},{"type":"AddLine","points":[[1.521240234375,20.309839248657227]]},{"type":"AddLine","points":[[1.521240234375,1.690155029296875]]},{"type":"CloseSubpath"},{"type":"MoveToPoint","points":[[1.521240234375,1.690155029296875]]}],"windingRule":0,"lineJoinStyle":0,"miterLimit":10},"isBackgroundTexture":true,"textBaseline":0,"isVerticalText":false,"textureType":5},"initialState":{"affineTransform":[1,0,0,1,0,0],"masksToBounds":false,"rotation":0,"scale":1,"position":{"pointX":36.978759765625,"pointY":9.309844970703125},"width":77,"sublayerTransform":[1,0,0,0,0,1,0,0,0,0,1,0,0,0,0,1],"contentsRect":{"y":0,"x":0,"width":1,"height":1},"opacity":1,"edgeAntialiasingMask":0,"height":22,"hidden":true,"anchorPoint":{"pointX":0.5,"pointY":0.5}},"texture":"A5CB58C0EC26082A6A1D79A500ACD787"}]},{"animations":[],"initialState":{"affineTransform":[1,0,0,1,0,0],"masksToBounds":false,"rotation":0,"scale":1,"position":{"pointX":409.00000762939453,"pointY":34.189841270446777},"width":656,"sublayerTransform":[1,0,0,0,0,1,0,0,0,0,1,0,0,0,0,1],"contentsRect":{"y":0,"x":0,"width":1,"height":1},"opacity":1,"edgeAntialiasingMask":251658240,"height":47,"hidden":false,"anchorPoint":{"pointX":0.5,"pointY":0.5}},"layers":[{"animations":[{"additive":false,"timeOffset":0,"beginTime":0,"repeatCount":0,"fillMode":"both","duration":3.75,"autoreverses":false,"animations":[{"repeatCount":0,"removedOnCompletion":true,"timingFunctions":[{"timingFunction":"EaseIn"},{"timingFunction":"custom","timingControlPoint1y":0,"timingControlPoint2x":0.57624423503875732,"timingControlPoint1x":0,"timingControlPoint2y":1},{"timingFunction":"custom","timingControlPoint1y":0.10000000149011612,"timingControlPoint2x":1,"timingControlPoint1x":0.25,"timingControlPoint2y":1}],"keyTimes":[0,0.45000000000000001,0.66700000000000004,1],"additive":false,"values":[{"scalar":0},{"scalar":1.125},{"scalar":0.95199999999999996},{"scalar":1}],"timeOffset":0,"autoreverses":false,"property":"transform.scale.xy","fillMode":"both","duration":1.875,"beginTime":0.7350260466337204},{"repeatCount":0,"removedOnCompletion":true,"from":{"scalar":0},"timingFunction":"EaseInEaseOut","additive":false,"timeOffset":0,"autoreverses":false,"property":"opacity","fillMode":"both","duration":1.875,"beginTime":0.7350260466337204,"to":{"scalar":1}},{"additive":false,"timeOffset":0,"beginTime":0,"from":{"scalar":false},"repeatCount":0,"fillMode":"both","duration":3.75,"autoreverses":false,"property":"hidden","to":{"scalar":false},"removedOnCompletion":true}],"removedOnCompletion":false}],"layers":[],"texturedRectangle":{"singleTextureOpacity":1,"textXHeight":0.67912765957446797,"textBaseline":0.93808175021029538,"isBackgroundTexture":true,"isVerticalText":false,"textColor":[0.098039217293262482,0.098039217293262482,0.098039217293262482,1],"textureType":6},"initialState":{"affineTransform":[1,0,0,1,0,0],"masksToBounds":false,"rotation":0,"scale":1,"position":{"pointX":330.99999237060547,"pointY":45.810158729553223},"width":656,"sublayerTransform":[1,0,0,0,0,1,0,0,0,0,1,0,0,0,0,1],"contentsRect":{"y":0,"x":0,"width":1,"height":1},"opacity":1,"edgeAntialiasingMask":0,"height":47,"hidden":true,"anchorPoint":{"pointX":0.5,"pointY":0.5}},"texture":"5925DF463A6EE8451015429E757C9BE9"}]},{"animations":[],"initialState":{"affineTransform":[1,0,0,1,0,0],"masksToBounds":false,"rotation":0,"scale":1,"position":{"pointX":413.60582733154297,"pointY":130.52897644042969},"width":594,"sublayerTransform":[1,0,0,0,0,1,0,0,0,0,1,0,0,0,0,1],"contentsRect":{"y":0,"x":0,"width":1,"height":1},"opacity":1,"edgeAntialiasingMask":251658240,"height":34,"hidden":false,"anchorPoint":{"pointX":0.5,"pointY":0.5}},"layers":[{"animations":[{"additive":false,"timeOffset":0,"beginTime":0,"repeatCount":0,"fillMode":"both","duration":3.75,"autoreverses":false,"animations":[{"repeatCount":0,"removedOnCompletion":true,"timingFunctions":[{"timingFunction":"EaseIn"},{"timingFunction":"custom","timingControlPoint1y":0,"timingControlPoint2x":0.57624423503875732,"timingControlPoint1x":0,"timingControlPoint2y":1},{"timingFunction":"custom","timingControlPoint1y":0.10000000149011612,"timingControlPoint2x":1,"timingControlPoint1x":0.25,"timingControlPoint2y":1}],"keyTimes":[0,0.45000000000000001,0.66700000000000004,1],"additive":false,"values":[{"scalar":0},{"scalar":1.125},{"scalar":0.95199999999999996},{"scalar":1}],"timeOffset":0,"autoreverses":false,"property":"transform.scale.xy","fillMode":"both","duration":1.875,"beginTime":0.73802462716897321},{"repeatCount":0,"removedOnCompletion":true,"from":{"scalar":0},"timingFunction":"EaseInEaseOut","additive":false,"timeOffset":0,"autoreverses":false,"property":"opacity","fillMode":"both","duration":1.875,"beginTime":0.73802462716897321,"to":{"scalar":1}},{"additive":false,"timeOffset":0,"beginTime":0,"from":{"scalar":false},"repeatCount":0,"fillMode":"both","duration":3.75,"autoreverses":false,"property":"hidden","to":{"scalar":false},"removedOnCompletion":true}],"removedOnCompletion":false}],"layers":[],"texturedRectangle":{"singleTextureOpacity":1,"textXHeight":0.52508823529411774,"textBaseline":0.78026402873151446,"isBackgroundTexture":true,"isVerticalText":false,"textColor":[0.098039217293262482,0.098039217293262482,0.098039217293262482,1],"textureType":6},"initialState":{"affineTransform":[1,0,0,1,0,0],"masksToBounds":false,"rotation":0,"scale":1,"position":{"pointX":296.39417266845703,"pointY":26.471023559570312},"width":594,"sublayerTransform":[1,0,0,0,0,1,0,0,0,0,1,0,0,0,0,1],"contentsRect":{"y":0,"x":0,"width":1,"height":1},"opacity":1,"edgeAntialiasingMask":0,"height":34,"hidden":true,"anchorPoint":{"pointX":0.5,"pointY":0.5}},"texture":"3ED2370E1D55959704E6F5A81484B4D9"}]},{"animations":[],"initialState":{"affineTransform":[1,0,0,1,0,0],"masksToBounds":false,"rotation":0,"scale":1,"position":{"pointX":661.10584259033203,"pointY":239.0108642578125},"width":1089,"sublayerTransform":[1,0,0,0,0,1,0,0,0,0,1,0,0,0,0,1],"contentsRect":{"y":0,"x":0,"width":1,"height":1},"opacity":1,"edgeAntialiasingMask":251658240,"height":171,"hidden":false,"anchorPoint":{"pointX":0.5,"pointY":0.5}},"layers":[{"animations":[{"additive":false,"timeOffset":0,"beginTime":0,"repeatCount":0,"fillMode":"both","duration":3.75,"autoreverses":false,"animations":[{"repeatCount":0,"removedOnCompletion":true,"timingFunctions":[{"timingFunction":"EaseIn"},{"timingFunction":"custom","timingControlPoint1y":0,"timingControlPoint2x":0.57624423503875732,"timingControlPoint1x":0,"timingControlPoint2y":1},{"timingFunction":"custom","timingControlPoint1y":0.10000000149011612,"timingControlPoint2x":1,"timingControlPoint1x":0.25,"timingControlPoint2y":1}],"keyTimes":[0,0.45000000000000001,0.66700000000000004,1],"additive":false,"values":[{"scalar":0},{"scalar":1.125},{"scalar":0.95199999999999996},{"scalar":1}],"timeOffset":0,"autoreverses":false,"property":"transform.scale.xy","fillMode":"both","duration":1.875,"beginTime":0.89915744960308075},{"repeatCount":0,"removedOnCompletion":true,"from":{"scalar":0},"timingFunction":"EaseInEaseOut","additive":false,"timeOffset":0,"autoreverses":false,"property":"opacity","fillMode":"both","duration":1.875,"beginTime":0.89915744960308075,"to":{"scalar":1}},{"additive":false,"timeOffset":0,"beginTime":0,"from":{"scalar":false},"repeatCount":0,"fillMode":"both","duration":3.75,"autoreverses":false,"property":"hidden","to":{"scalar":false},"removedOnCompletion":true}],"removedOnCompletion":false}],"layers":[],"texturedRectangle":{"singleTextureOpacity":1,"textXHeight":0.081473684210526323,"textBaseline":1.2111746473619116,"isBackgroundTexture":true,"isVerticalText":false,"textColor":[0.098039217293262482,0.098039217293262482,0.098039217293262482,1],"textureType":6},"initialState":{"affineTransform":[1,0,0,1,0,0],"masksToBounds":false,"rotation":0,"scale":1,"position":{"pointX":543.89415740966797,"pointY":92.9891357421875},"width":1089,"sublayerTransform":[1,0,0,0,0,1,0,0,0,0,1,0,0,0,0,1],"contentsRect":{"y":0,"x":0,"width":1,"height":1},"opacity":1,"edgeAntialiasingMask":0,"height":171,"hidden":true,"anchorPoint":{"pointX":0.5,"pointY":0.5}},"texture":"765E2EA5592FB78B20F4EC16AC7FD7A0"}]},{"animations":[],"initialState":{"affineTransform":[1,0,0,1,0,0],"masksToBounds":false,"rotation":0,"scale":1,"position":{"pointX":63.991968154907227,"pointY":138.88558959960938},"width":67,"sublayerTransform":[1,0,0,0,0,1,0,0,0,0,1,0,0,0,0,1],"contentsRect":{"y":0,"x":0,"width":1,"height":1},"opacity":1,"edgeAntialiasingMask":251658240,"height":67,"hidden":false,"anchorPoint":{"pointX":0.5,"pointY":0.5}},"layers":[{"animations":[{"additive":false,"timeOffset":0,"beginTime":0,"repeatCount":0,"fillMode":"both","duration":3.75,"autoreverses":false,"animations":[{"repeatCount":0,"removedOnCompletion":true,"timingFunctions":[{"timingFunction":"EaseIn"},{"timingFunction":"custom","timingControlPoint1y":0,"timingControlPoint2x":0.57624423503875732,"timingControlPoint1x":0,"timingControlPoint2y":1},{"timingFunction":"custom","timingControlPoint1y":0.10000000149011612,"timingControlPoint2x":1,"timingControlPoint1x":0.25,"timingControlPoint2y":1}],"keyTimes":[0,0.45000000000000001,0.66700000000000004,1],"additive":false,"values":[{"scalar":0},{"scalar":1.125},{"scalar":0.95199999999999996},{"scalar":1}],"timeOffset":0,"autoreverses":false,"property":"transform.scale.xy","fillMode":"both","duration":1.875,"beginTime":0.51041143760085106},{"repeatCount":0,"removedOnCompletion":true,"from":{"scalar":0},"timingFunction":"EaseInEaseOut","additive":false,"timeOffset":0,"autoreverses":false,"property":"opacity","fillMode":"both","duration":1.875,"beginTime":0.51041143760085106,"to":{"scalar":1}},{"additive":false,"timeOffset":0,"beginTime":0,"from":{"scalar":false},"repeatCount":0,"fillMode":"both","duration":3.75,"autoreverses":false,"property":"hidden","to":{"scalar":false},"removedOnCompletion":true}],"removedOnCompletion":false}],"layers":[],"texturedRectangle":{"isBackgroundTexture":true,"singleTextureOpacity":1,"textureType":5,"textBaseline":0,"textXHeight":0,"isVerticalText":false},"initialState":{"affineTransform":[1,0,0,1,0,0],"masksToBounds":false,"rotation":0,"scale":1,"position":{"pointX":32.008031845092773,"pointY":32.114410400390625},"width":67,"sublayerTransform":[1,0,0,0,0,1,0,0,0,0,1,0,0,0,0,1],"contentsRect":{"y":0,"x":0,"width":1,"height":1},"opacity":1,"edgeAntialiasingMask":0,"height":67,"hidden":true,"anchorPoint":{"pointX":0.5,"pointY":0.5}},"texture":"AD6454C95626FBA9C44ECC02468B867F"}]},{"animations":[],"initialState":{"affineTransform":[1,0,0,1,0,0],"masksToBounds":false,"rotation":0,"scale":1,"position":{"pointX":364.10587310791016,"pointY":345.32330322265625},"width":495,"sublayerTransform":[1,0,0,0,0,1,0,0,0,0,1,0,0,0,0,1],"contentsRect":{"y":0,"x":0,"width":1,"height":1},"opacity":1,"edgeAntialiasingMask":251658240,"height":72,"hidden":false,"anchorPoint":{"pointX":0.5,"pointY":0.5}},"layers":[{"animations":[{"additive":false,"timeOffset":0,"beginTime":0,"repeatCount":0,"fillMode":"both","duration":3.75,"autoreverses":false,"animations":[{"repeatCount":0,"removedOnCompletion":true,"timingFunctions":[{"timingFunction":"EaseIn"},{"timingFunction":"custom","timingControlPoint1y":0,"timingControlPoint2x":0.57624423503875732,"timingControlPoint1x":0,"timingControlPoint2y":1},{"timingFunction":"custom","timingControlPoint1y":0.10000000149011612,"timingControlPoint2x":1,"timingControlPoint1x":0.25,"timingControlPoint2y":1}],"keyTimes":[0,0.45000000000000001,0.66700000000000004,1],"additive":false,"values":[{"scalar":0},{"scalar":1.125},{"scalar":0.95199999999999996},{"scalar":1}],"timeOffset":0,"autoreverses":false,"property":"transform.scale.xy","fillMode":"both","duration":1.875,"beginTime":0.70579809447129571},{"repeatCount":0,"removedOnCompletion":true,"from":{"scalar":0},"timingFunction":"EaseInEaseOut","additive":false,"timeOffset":0,"autoreverses":false,"property":"opacity","fillMode":"both","duration":1.875,"beginTime":0.70579809447129571,"to":{"scalar":1}},{"additive":false,"timeOffset":0,"beginTime":0,"from":{"scalar":false},"repeatCount":0,"fillMode":"both","duration":3.75,"autoreverses":false,"property":"hidden","to":{"scalar":false},"removedOnCompletion":true}],"removedOnCompletion":false}],"layers":[],"texturedRectangle":{"singleTextureOpacity":1,"textXHeight":0.24795833333333336,"textBaseline":1.6156014410985842,"isBackgroundTexture":true,"isVerticalText":false,"textColor":[0.098039217293262482,0.098039217293262482,0.098039217293262482,1],"textureType":6},"initialState":{"affineTransform":[1,0,0,1,0,0],"masksToBounds":false,"rotation":0,"scale":1,"position":{"pointX":246.89412689208984,"pointY":45.67669677734375},"width":495,"sublayerTransform":[1,0,0,0,0,1,0,0,0,0,1,0,0,0,0,1],"contentsRect":{"y":0,"x":0,"width":1,"height":1},"opacity":1,"edgeAntialiasingMask":0,"height":72,"hidden":true,"anchorPoint":{"pointX":0.5,"pointY":0.5}},"texture":"1FA82269F68C3079E3607ACE6DA313F7"}]},{"animations":[],"initialState":{"affineTransform":[1,0,0,1,0,0],"masksToBounds":false,"rotation":0,"scale":1,"position":{"pointX":66.491968154907227,"pointY":343.65692138671875},"width":72,"sublayerTransform":[1,0,0,0,0,1,0,0,0,0,1,0,0,0,0,1],"contentsRect":{"y":0,"x":0,"width":1,"height":1},"opacity":1,"edgeAntialiasingMask":251658240,"height":76,"hidden":false,"anchorPoint":{"pointX":0.5,"pointY":0.5}},"layers":[{"animations":[{"additive":false,"timeOffset":0,"beginTime":0,"repeatCount":0,"fillMode":"both","duration":3.75,"autoreverses":false,"animations":[{"repeatCount":0,"removedOnCompletion":true,"timingFunctions":[{"timingFunction":"EaseIn"},{"timingFunction":"custom","timingControlPoint1y":0,"timingControlPoint2x":0.57624423503875732,"timingControlPoint1x":0,"timingControlPoint2y":1},{"timingFunction":"custom","timingControlPoint1y":0.10000000149011612,"timingControlPoint2x":1,"timingControlPoint1x":0.25,"timingControlPoint2y":1}],"keyTimes":[0,0.45000000000000001,0.66700000000000004,1],"additive":false,"values":[{"scalar":0},{"scalar":1.125},{"scalar":0.95199999999999996},{"scalar":1}],"timeOffset":0,"autoreverses":false,"property":"transform.scale.xy","fillMode":"both","duration":1.875,"beginTime":0.51203904176751769},{"repeatCount":0,"removedOnCompletion":true,"from":{"scalar":0},"timingFunction":"EaseInEaseOut","additive":false,"timeOffset":0,"autoreverses":false,"property":"opacity","fillMode":"both","duration":1.875,"beginTime":0.51203904176751769,"to":{"scalar":1}},{"additive":false,"timeOffset":0,"beginTime":0,"from":{"scalar":false},"repeatCount":0,"fillMode":"both","duration":3.75,"autoreverses":false,"property":"hidden","to":{"scalar":false},"removedOnCompletion":true}],"removedOnCompletion":false}],"layers":[],"texturedRectangle":{"isBackgroundTexture":true,"singleTextureOpacity":1,"textureType":5,"textBaseline":0,"textXHeight":0,"isVerticalText":false},"initialState":{"affineTransform":[1,0,0,1,0,0],"masksToBounds":false,"rotation":0,"scale":1,"position":{"pointX":34.508031845092773,"pointY":36.34307861328125},"width":72,"sublayerTransform":[1,0,0,0,0,1,0,0,0,0,1,0,0,0,0,1],"contentsRect":{"y":0,"x":0,"width":1,"height":1},"opacity":1,"edgeAntialiasingMask":0,"height":76,"hidden":true,"anchorPoint":{"pointX":0.5,"pointY":0.5}},"texture":"713FBE56E9B67C4EE271793F37875EE2"}]},{"animations":[],"initialState":{"affineTransform":[1,0,0,1,0,0],"masksToBounds":false,"rotation":0,"scale":1,"position":{"pointX":632.10582733154297,"pointY":435.0279541015625},"width":1031,"sublayerTransform":[1,0,0,0,0,1,0,0,0,0,1,0,0,0,0,1],"contentsRect":{"y":0,"x":0,"width":1,"height":1},"opacity":1,"edgeAntialiasingMask":251658240,"height":170,"hidden":false,"anchorPoint":{"pointX":0.5,"pointY":0.5}},"layers":[{"animations":[{"additive":false,"timeOffset":0,"beginTime":0,"repeatCount":0,"fillMode":"both","duration":3.75,"autoreverses":false,"animations":[{"repeatCount":0,"removedOnCompletion":true,"timingFunctions":[{"timingFunction":"EaseIn"},{"timingFunction":"custom","timingControlPoint1y":0,"timingControlPoint2x":0.57624423503875732,"timingControlPoint1x":0,"timingControlPoint2y":1},{"timingFunction":"custom","timingControlPoint1y":0.10000000149011612,"timingControlPoint2x":1,"timingControlPoint1x":0.25,"timingControlPoint2y":1}],"keyTimes":[0,0.45000000000000001,0.66700000000000004,1],"additive":false,"values":[{"scalar":0},{"scalar":1.125},{"scalar":0.95199999999999996},{"scalar":1}],"timeOffset":0,"autoreverses":false,"property":"transform.scale.xy","fillMode":"both","duration":1.875,"beginTime":0.88027723133563995},{"repeatCount":0,"removedOnCompletion":true,"from":{"scalar":0},"timingFunction":"EaseInEaseOut","additive":false,"timeOffset":0,"autoreverses":false,"property":"opacity","fillMode":"both","duration":1.875,"beginTime":0.88027723133563995,"to":{"scalar":1}},{"additive":false,"timeOffset":0,"beginTime":0,"from":{"scalar":false},"repeatCount":0,"fillMode":"both","duration":3.75,"autoreverses":false,"property":"hidden","to":{"scalar":false},"removedOnCompletion":true}],"removedOnCompletion":false}],"layers":[],"texturedRectangle":{"singleTextureOpacity":1,"textXHeight":0.08195294117647059,"textBaseline":1.2154585561331581,"isBackgroundTexture":true,"isVerticalText":false,"textColor":[0.098039217293262482,0.098039217293262482,0.098039217293262482,1],"textureType":6},"initialState":{"affineTransform":[1,0,0,1,0,0],"masksToBounds":false,"rotation":0,"scale":1,"position":{"pointX":514.89417266845703,"pointY":92.9720458984375},"width":1031,"sublayerTransform":[1,0,0,0,0,1,0,0,0,0,1,0,0,0,0,1],"contentsRect":{"y":0,"x":0,"width":1,"height":1},"opacity":1,"edgeAntialiasingMask":0,"height":170,"hidden":true,"anchorPoint":{"pointX":0.5,"pointY":0.5}},"texture":"4C0554448575FCE60EE0460D8D53B606"}]},{"animations":[],"initialState":{"affineTransform":[1,0,0,1,0,0],"masksToBounds":false,"rotation":0,"scale":1,"position":{"pointX":397.10581970214844,"pointY":561.62860107421875},"width":561,"sublayerTransform":[1,0,0,0,0,1,0,0,0,0,1,0,0,0,0,1],"contentsRect":{"y":0,"x":0,"width":1,"height":1},"opacity":1,"edgeAntialiasingMask":251658240,"height":34,"hidden":false,"anchorPoint":{"pointX":0.5,"pointY":0.5}},"layers":[{"animations":[{"additive":false,"timeOffset":0,"beginTime":0,"repeatCount":0,"fillMode":"both","duration":3.75,"autoreverses":false,"animations":[{"repeatCount":0,"removedOnCompletion":true,"timingFunctions":[{"timingFunction":"EaseIn"},{"timingFunction":"custom","timingControlPoint1y":0,"timingControlPoint2x":0.57624423503875732,"timingControlPoint1x":0,"timingControlPoint2y":1},{"timingFunction":"custom","timingControlPoint1y":0.10000000149011612,"timingControlPoint2x":1,"timingControlPoint1x":0.25,"timingControlPoint2y":1}],"keyTimes":[0,0.45000000000000001,0.66700000000000004,1],"additive":false,"values":[{"scalar":0},{"scalar":1.125},{"scalar":0.95199999999999996},{"scalar":1}],"timeOffset":0,"autoreverses":false,"property":"transform.scale.xy","fillMode":"both","duration":1.875,"beginTime":0.72728243470191956},{"repeatCount":0,"removedOnCompletion":true,"from":{"scalar":0},"timingFunction":"EaseInEaseOut","additive":false,"timeOffset":0,"autoreverses":false,"property":"opacity","fillMode":"both","duration":1.875,"beginTime":0.72728243470191956,"to":{"scalar":1}},{"additive":false,"timeOffset":0,"beginTime":0,"from":{"scalar":false},"repeatCount":0,"fillMode":"both","duration":3.75,"autoreverses":false,"property":"hidden","to":{"scalar":false},"removedOnCompletion":true}],"removedOnCompletion":false}],"layers":[],"texturedRectangle":{"singleTextureOpacity":1,"textXHeight":0.52508823529411774,"textBaseline":2.1067235767841339,"isBackgroundTexture":true,"isVerticalText":false,"textColor":[0.098039217293262482,0.098039217293262482,0.098039217293262482,1],"textureType":6},"initialState":{"affineTransform":[1,0,0,1,0,0],"masksToBounds":false,"rotation":0,"scale":1,"position":{"pointX":280.89418029785156,"pointY":26.37139892578125},"width":561,"sublayerTransform":[1,0,0,0,0,1,0,0,0,0,1,0,0,0,0,1],"contentsRect":{"y":0,"x":0,"width":1,"height":1},"opacity":1,"edgeAntialiasingMask":0,"height":34,"hidden":true,"anchorPoint":{"pointX":0.5,"pointY":0.5}},"texture":"F1F1BD7DF227BF49CD6A9F7B48A28CFE"}]},{"animations":[],"initialState":{"affineTransform":[1,0,0,1,0,0],"masksToBounds":false,"rotation":0,"scale":1,"position":{"pointX":66.491968154907227,"pointY":577.67401123046875},"width":72,"sublayerTransform":[1,0,0,0,0,1,0,0,0,0,1,0,0,0,0,1],"contentsRect":{"y":0,"x":0,"width":1,"height":1},"opacity":1,"edgeAntialiasingMask":251658240,"height":76,"hidden":false,"anchorPoint":{"pointX":0.5,"pointY":0.5}},"layers":[{"animations":[{"additive":false,"timeOffset":0,"beginTime":0,"repeatCount":0,"fillMode":"both","duration":3.75,"autoreverses":false,"animations":[{"repeatCount":0,"removedOnCompletion":true,"timingFunctions":[{"timingFunction":"EaseIn"},{"timingFunction":"custom","timingControlPoint1y":0,"timingControlPoint2x":0.57624423503875732,"timingControlPoint1x":0,"timingControlPoint2y":1},{"timingFunction":"custom","timingControlPoint1y":0.10000000149011612,"timingControlPoint2x":1,"timingControlPoint1x":0.25,"timingControlPoint2y":1}],"keyTimes":[0,0.45000000000000001,0.66700000000000004,1],"additive":false,"values":[{"scalar":0},{"scalar":1.125},{"scalar":0.95199999999999996},{"scalar":1}],"timeOffset":0,"autoreverses":false,"property":"transform.scale.xy","fillMode":"both","duration":1.875,"beginTime":0.51203904176751769},{"repeatCount":0,"removedOnCompletion":true,"from":{"scalar":0},"timingFunction":"EaseInEaseOut","additive":false,"timeOffset":0,"autoreverses":false,"property":"opacity","fillMode":"both","duration":1.875,"beginTime":0.51203904176751769,"to":{"scalar":1}},{"additive":false,"timeOffset":0,"beginTime":0,"from":{"scalar":false},"repeatCount":0,"fillMode":"both","duration":3.75,"autoreverses":false,"property":"hidden","to":{"scalar":false},"removedOnCompletion":true}],"removedOnCompletion":false}],"layers":[],"texturedRectangle":{"isBackgroundTexture":true,"singleTextureOpacity":1,"textureType":5,"textBaseline":0,"textXHeight":0,"isVerticalText":false},"initialState":{"affineTransform":[1,0,0,1,0,0],"masksToBounds":false,"rotation":0,"scale":1,"position":{"pointX":34.508031845092773,"pointY":36.32598876953125},"width":72,"sublayerTransform":[1,0,0,0,0,1,0,0,0,0,1,0,0,0,0,1],"contentsRect":{"y":0,"x":0,"width":1,"height":1},"opacity":1,"edgeAntialiasingMask":0,"height":76,"hidden":true,"anchorPoint":{"pointX":0.5,"pointY":0.5}},"texture":"5CF8AE5C26095294EC1BE0FB30046E9E"}]},{"animations":[],"initialState":{"affineTransform":[1,0,0,1,0,0],"masksToBounds":false,"rotation":0,"scale":1,"position":{"pointX":656.10581970214844,"pointY":683.79833984375},"width":1079,"sublayerTransform":[1,0,0,0,0,1,0,0,0,0,1,0,0,0,0,1],"contentsRect":{"y":0,"x":0,"width":1,"height":1},"opacity":1,"edgeAntialiasingMask":251658240,"height":177,"hidden":false,"anchorPoint":{"pointX":0.5,"pointY":0.5}},"layers":[{"animations":[{"additive":false,"timeOffset":0,"beginTime":0,"repeatCount":0,"fillMode":"both","duration":3.75,"autoreverses":false,"animations":[{"repeatCount":0,"removedOnCompletion":true,"timingFunctions":[{"timingFunction":"EaseIn"},{"timingFunction":"custom","timingControlPoint1y":0,"timingControlPoint2x":0.57624423503875732,"timingControlPoint1x":0,"timingControlPoint2y":1},{"timingFunction":"custom","timingControlPoint1y":0.10000000149011612,"timingControlPoint2x":1,"timingControlPoint1x":0.25,"timingControlPoint2y":1}],"keyTimes":[0,0.45000000000000001,0.66700000000000004,1],"additive":false,"values":[{"scalar":0},{"scalar":1.125},{"scalar":0.95199999999999996},{"scalar":1}],"timeOffset":0,"autoreverses":false,"property":"transform.scale.xy","fillMode":"both","duration":1.875,"beginTime":0.8959022263685863},{"repeatCount":0,"removedOnCompletion":true,"from":{"scalar":0},"timingFunction":"EaseInEaseOut","additive":false,"timeOffset":0,"autoreverses":false,"property":"opacity","fillMode":"both","duration":1.875,"beginTime":0.8959022263685863,"to":{"scalar":1}},{"additive":false,"timeOffset":0,"beginTime":0,"from":{"scalar":false},"repeatCount":0,"fillMode":"both","duration":3.75,"autoreverses":false,"property":"hidden","to":{"scalar":false},"removedOnCompletion":true}],"removedOnCompletion":false}],"layers":[],"texturedRectangle":{"singleTextureOpacity":1,"textXHeight":0.078711864406779658,"textBaseline":0.95987762872782134,"isBackgroundTexture":true,"isVerticalText":false,"textColor":[0.098039217293262482,0.098039217293262482,0.098039217293262482,1],"textureType":6},"initialState":{"affineTransform":[1,0,0,1,0,0],"masksToBounds":false,"rotation":0,"scale":1,"position":{"pointX":538.89418029785156,"pointY":96.20166015625},"width":1079,"sublayerTransform":[1,0,0,0,0,1,0,0,0,0,1,0,0,0,0,1],"contentsRect":{"y":0,"x":0,"width":1,"height":1},"opacity":1,"edgeAntialiasingMask":0,"height":177,"hidden":true,"anchorPoint":{"pointX":0.5,"pointY":0.5}},"texture":"99B08C3706E8C4B69AC19EB1564417ED"}]},{"animations":[],"initialState":{"affineTransform":[1,0,0,1,0,0],"masksToBounds":false,"rotation":0,"scale":1,"position":{"pointX":-481.39499304059063,"pointY":673.58799340960445},"width":1221,"sublayerTransform":[1,0,0,0,0,1,0,0,0,0,1,0,0,0,0,1],"contentsRect":{"y":0,"x":0,"width":1,"height":1},"opacity":1,"edgeAntialiasingMask":251658240,"height":1221,"hidden":false,"anchorPoint":{"pointX":0.5,"pointY":0.5}},"layers":[{"animations":[{"additive":false,"timeOffset":0,"beginTime":0,"repeatCount":0,"fillMode":"both","duration":3.75,"autoreverses":false,"animations":[{"repeatCount":0,"removedOnCompletion":true,"timingFunctions":[{"timingFunction":"EaseIn"},{"timingFunction":"custom","timingControlPoint1y":0,"timingControlPoint2x":0.57624423503875732,"timingControlPoint1x":0,"timingControlPoint2y":1},{"timingFunction":"custom","timingControlPoint1y":0.10000000149011612,"timingControlPoint2x":1,"timingControlPoint1x":0.25,"timingControlPoint2y":1}],"keyTimes":[0,0.45000000000000001,0.66700000000000004,1],"additive":false,"values":[{"scalar":0},{"scalar":1.125},{"scalar":0.95199999999999996},{"scalar":1}],"timeOffset":0,"autoreverses":false,"property":"transform.scale.xy","fillMode":"both","duration":1.875,"beginTime":0.15534180140586545},{"repeatCount":0,"removedOnCompletion":true,"from":{"scalar":0},"timingFunction":"EaseInEaseOut","additive":false,"timeOffset":0,"autoreverses":false,"property":"opacity","fillMode":"both","duration":1.875,"beginTime":0.15534180140586545,"to":{"scalar":1}},{"additive":false,"timeOffset":0,"beginTime":0,"from":{"scalar":false},"repeatCount":0,"fillMode":"both","duration":3.75,"autoreverses":false,"property":"hidden","to":{"scalar":false},"removedOnCompletion":true}],"removedOnCompletion":false}],"layers":[],"texturedRectangle":{"singleTextureOpacity":1,"textXHeight":0,"shapePath":{"lineWidth":1,"flatness":0.59999999999999998,"lineCapStyle":0,"elements":[{"type":"MoveToPoint","points":[[414.31708070820491,224.19712085482263]]},{"type":"AddCurve","points":[[201.14011738237286,332.38290143547692],[116.02835382397313,592.89763382240835],[224.21413440462743,806.07459714824051]]},{"type":"AddCurve","points":[[332.39990807990262,1019.251546867222],[592.91464737221327,1104.3633240324723],[806.09161069804543,996.17754345181788]]},{"type":"AddCurve","points":[[1019.2685604170268,887.99176977654281],[1104.380330676898,627.47701687738163],[996.1945570016228,414.30006715840011]]},{"type":"AddCurve","points":[[888.0087764209685,201.12310383256801],[627.49403042718643,116.01134717954744],[414.31708070820491,224.19712085482263]]},{"type":"CloseSubpath"},{"type":"MoveToPoint","points":[[414.31708070820491,224.19712085482263]]}],"windingRule":0,"lineJoinStyle":0,"miterLimit":10},"isBackgroundTexture":true,"textBaseline":0,"isVerticalText":false,"textureType":5},"initialState":{"affineTransform":[1,0,0,1,0,0],"masksToBounds":false,"rotation":0,"scale":1,"position":{"pointX":609.39499304059063,"pointY":609.41200659039555},"width":1221,"sublayerTransform":[1,0,0,0,0,1,0,0,0,0,1,0,0,0,0,1],"contentsRect":{"y":0,"x":0,"width":1,"height":1},"opacity":1,"edgeAntialiasingMask":0,"height":1221,"hidden":true,"anchorPoint":{"pointX":0.5,"pointY":0.5}},"texture":"35BEB27BCFD2A0671D05F54DF7529643"}]},{"animations":[],"initialState":{"affineTransform":[1,0,0,1,0,0],"masksToBounds":false,"rotation":0,"scale":1,"position":{"pointX":139.08324924155897,"pointY":802.25564787777023},"width":1759,"sublayerTransform":[1,0,0,0,0,1,0,0,0,0,1,0,0,0,0,1],"contentsRect":{"y":0,"x":0,"width":1,"height":1},"opacity":1,"edgeAntialiasingMask":251658240,"height":1769,"hidden":false,"anchorPoint":{"pointX":0.5,"pointY":0.5}},"layers":[{"animations":[{"additive":false,"timeOffset":0,"beginTime":0,"repeatCount":0,"fillMode":"both","duration":3.75,"autoreverses":false,"animations":[{"repeatCount":0,"removedOnCompletion":true,"timingFunctions":[{"timingFunction":"EaseIn"},{"timingFunction":"custom","timingControlPoint1y":0,"timingControlPoint2x":0.57624423503875732,"timingControlPoint1x":0,"timingControlPoint2y":1},{"timingFunction":"custom","timingControlPoint1y":0.10000000149011612,"timingControlPoint2x":1,"timingControlPoint1x":0.25,"timingControlPoint2y":1}],"keyTimes":[0,0.45000000000000001,0.66700000000000004,1],"additive":false,"values":[{"scalar":0},{"scalar":1.125},{"scalar":0.95199999999999996},{"scalar":1}],"timeOffset":0,"autoreverses":false,"property":"transform.scale.xy","fillMode":"both","duration":1.875,"beginTime":0.55929899039163999},{"repeatCount":0,"removedOnCompletion":true,"from":{"scalar":0},"timingFunction":"EaseInEaseOut","additive":false,"timeOffset":0,"autoreverses":false,"property":"opacity","fillMode":"both","duration":1.875,"beginTime":0.55929899039163999,"to":{"scalar":1}},{"additive":false,"timeOffset":0,"beginTime":0,"from":{"scalar":false},"repeatCount":0,"fillMode":"both","duration":3.75,"autoreverses":false,"property":"hidden","to":{"scalar":false},"removedOnCompletion":true}],"removedOnCompletion":false}],"layers":[],"texturedRectangle":{"singleTextureOpacity":1,"textXHeight":0,"shapePath":{"lineWidth":1,"flatness":0.59999999999999998,"lineCapStyle":0,"elements":[{"type":"MoveToPoint","points":[[411.88395517272335,519.77980538225074]]},{"type":"AddCurve","points":[[200.97774738712678,790.17965173825337],[239.32959639322678,1172.6506465620987],[497.54442190203844,1374.0527937008337]]},{"type":"AddCurve","points":[[755.75927147427558,1575.4549596085358],[1136.0561860794678,1519.5212181052348],[1346.9623938650643,1249.1213717492319]]},{"type":"AddCurve","points":[[1557.8686016506608,978.72152539322929],[1519.5182435982529,596.25045499155021],[1261.3033940260161,394.84828908384827]]},{"type":"AddCurve","points":[[1003.0885685172043,193.44614194511325],[622.79016295831991,249.379959026248],[411.88395517272335,519.77980538225074]]},{"type":"CloseSubpath"},{"type":"MoveToPoint","points":[[411.88395517272335,519.77980538225074]]}],"windingRule":0,"lineJoinStyle":0,"miterLimit":10},"isBackgroundTexture":true,"textBaseline":0,"isVerticalText":false,"textureType":5},"initialState":{"affineTransform":[1,0,0,1,0,0],"masksToBounds":false,"rotation":0,"scale":1,"position":{"pointX":877.91675075844103,"pointY":882.74435212222977},"width":1759,"sublayerTransform":[1,0,0,0,0,1,0,0,0,0,1,0,0,0,0,1],"contentsRect":{"y":0,"x":0,"width":1,"height":1},"opacity":1,"edgeAntialiasingMask":0,"height":1769,"hidden":true,"anchorPoint":{"pointX":0.5,"pointY":0.5}},"texture":"7417B7E31B0B5A22D6C7FCE2448F6A8B"}]}]},"effects":[],"duration":3.75,"type":"transition","attributes":{"direction":11},"name":"apple:ca-pop","objectID":"0"}],"automaticPlay":false,"hyperlinks":[],"accessibility":[{"text":"INTRODUCTION","targetRectangle":{"y":67.323539733886719,"x":167.44480895996094,"width":522.21300034332262,"height":57}},{"text":"The QR Attendance System aims to modernize attendance tracking by integrating QR code technology with a network-based approach. In educational institutions, accurate attendance records are crucial for administrative purposes and student evaluation. Traditional methods often fall short due to their manual nature, leading to inefficiencies and errors. This project addresses these issues by providing a robust, automated solution that enhances both accuracy and security","targetRectangle":{"y":146.21676635742188,"x":156.57368469238281,"width":1077.1939855875971,"height":258}},{"text":"Educational institutions rely on accurate attendance records for various administrative and academic purposes. However, traditional methods like manual roll calls or paper-based sign-ins are prone to human error, time-consuming, and lack security. There is a critical need for an automated, secure, and efficient system that can streamline the attendance process while maintaining data integrity and accessibility","targetRectangle":{"y":427.56497192382812,"x":150.46623229980469,"width":1072.7619852776529,"height":215}}],"baseLayer":{"animations":[],"initialState":{"affineTransform":[1,0,0,1,0,0],"masksToBounds":false,"rotation":0,"scale":1,"position":{"pointX":720,"pointY":405},"width":1440,"sublayerTransform":[1,0,0,0,0,1,0,0,0,0,1,0,0,0,0,1],"contentsRect":{"y":0,"x":0,"width":1,"height":1},"opacity":1,"edgeAntialiasingMask":251658240,"height":810,"hidden":false,"anchorPoint":{"pointX":0.5,"pointY":0.5}},"objectID":"0","layers":[{"animations":[],"initialState":{"affineTransform":[1,0,0,1,0,0],"masksToBounds":false,"rotation":0,"scale":1,"position":{"pointX":720,"pointY":405},"width":1440,"sublayerTransform":[1,0,0,0,0,1,0,0,0,0,1,-0.00046677216622367974,0,0,0,1],"contentsRect":{"y":0,"x":0,"width":1,"height":1},"opacity":1,"edgeAntialiasingMask":251658240,"height":810,"hidden":false,"anchorPoint":{"pointX":0.5,"pointY":0.5}},"layers":[{"animations":[],"initialState":{"affineTransform":[1,0,0,1,0,0],"masksToBounds":false,"rotation":0,"scale":1,"position":{"pointX":720,"pointY":405},"width":1440,"sublayerTransform":[1,0,0,0,0,1,0,0,0,0,1,0,0,0,0,1],"contentsRect":{"y":0,"x":0,"width":1,"height":1},"opacity":1,"edgeAntialiasingMask":251658240,"height":810,"hidden":false,"anchorPoint":{"pointX":0.5,"pointY":0.5}},"layers":[{"animations":[],"layers":[],"texturedRectangle":{"isBackgroundTexture":true,"singleTextureOpacity":1,"textureType":1,"textBaseline":0,"textXHeight":0,"isVerticalText":false},"initialState":{"affineTransform":[1,0,0,1,0,0],"masksToBounds":false,"rotation":0,"scale":1,"position":{"pointX":720,"pointY":405},"width":1440,"sublayerTransform":[1,0,0,0,0,1,0,0,0,0,1,0,0,0,0,1],"contentsRect":{"y":0,"x":0,"width":1,"height":1},"opacity":1,"edgeAntialiasingMask":0,"height":810,"hidden":false,"anchorPoint":{"pointX":0.5,"pointY":0.5}},"texture":"B154F0DC13C3220DDA3B7C1CFDB4510A"}]},{"animations":[],"initialState":{"affineTransform":[1,0,0,1,0,0],"masksToBounds":false,"rotation":0,"scale":1,"position":{"pointX":720,"pointY":405},"width":1440,"sublayerTransform":[1,0,0,0,0,1,0,0,0,0,1,0,0,0,0,1],"contentsRect":{"y":0,"x":0,"width":1,"height":1},"opacity":1,"edgeAntialiasingMask":251658240,"height":810,"hidden":false,"anchorPoint":{"pointX":0.5,"pointY":0.5}},"layers":[{"animations":[],"layers":[],"texturedRectangle":{"isBackgroundTexture":true,"singleTextureOpacity":1,"textureType":1,"textBaseline":0,"textXHeight":0,"isVerticalText":false},"initialState":{"affineTransform":[1,0,0,1,0,0],"masksToBounds":false,"rotation":0,"scale":1,"position":{"pointX":720,"pointY":405},"width":1440,"sublayerTransform":[1,0,0,0,0,1,0,0,0,0,1,0,0,0,0,1],"contentsRect":{"y":0,"x":0,"width":1,"height":1},"opacity":1,"edgeAntialiasingMask":0,"height":810,"hidden":false,"anchorPoint":{"pointX":0.5,"pointY":0.5}},"texture":"B154F0DC13C3220DDA3B7C1CFDB4510A"}]}]},{"animations":[],"initialState":{"affineTransform":[1,0,0,1,0,0],"masksToBounds":false,"rotation":0,"scale":1,"position":{"pointX":1323.021240234375,"pointY":82.690155029296875},"width":77,"sublayerTransform":[1,0,0,0,0,1,0,0,0,0,1,0,0,0,0,1],"contentsRect":{"y":0,"x":0,"width":1,"height":1},"opacity":1,"edgeAntialiasingMask":251658240,"height":22,"hidden":false,"anchorPoint":{"pointX":0.5,"pointY":0.5}},"layers":[{"animations":[],"initialState":{"affineTransform":[1,0,0,1,0,0],"masksToBounds":false,"rotation":0,"scale":1,"position":{"pointX":-564.521240234375,"pointY":333.30984497070312},"width":77,"sublayerTransform":[1,0,0,0,0,1,0,0,0,0,1,-0.00046677216622367974,0,0,0,1],"contentsRect":{"y":0,"x":0,"width":1,"height":1},"opacity":1,"edgeAntialiasingMask":251658240,"height":22,"hidden":false,"anchorPoint":{"pointX":-7.3314446783685066,"pointY":15.150447498668324}},"layers":[{"animations":[],"layers":[],"texturedRectangle":{"singleTextureOpacity":1,"textXHeight":0,"shapePath":{"lineWidth":1,"flatness":0.59999999999999998,"lineCapStyle":0,"elements":[{"type":"MoveToPoint","points":[[1.521240234375,1.690155029296875]]},{"type":"AddLine","points":[[75.999977111816406,1.690155029296875]]},{"type":"AddLine","points":[[75.999977111816406,20.309839248657227]]},{"type":"AddLine","points":[[1.521240234375,20.309839248657227]]},{"type":"AddLine","points":[[1.521240234375,1.690155029296875]]},{"type":"CloseSubpath"},{"type":"MoveToPoint","points":[[1.521240234375,1.690155029296875]]}],"windingRule":0,"lineJoinStyle":0,"miterLimit":10},"isBackgroundTexture":true,"textBaseline":0,"isVerticalText":false,"textureType":5},"initialState":{"affineTransform":[1,0,0,1,0,0],"masksToBounds":false,"rotation":0,"scale":1,"position":{"pointX":36.978759765625,"pointY":9.309844970703125},"width":77,"sublayerTransform":[1,0,0,0,0,1,0,0,0,0,1,0,0,0,0,1],"contentsRect":{"y":0,"x":0,"width":1,"height":1},"opacity":1,"edgeAntialiasingMask":0,"height":22,"hidden":false,"anchorPoint":{"pointX":0.5,"pointY":0.5}},"texture":"A5CB58C0EC26082A6A1D79A500ACD787"}]}]},{"animations":[],"initialState":{"affineTransform":[1,0,0,1,0,0],"masksToBounds":false,"rotation":0,"scale":1,"position":{"pointX":685.96623229980469,"pointY":528.06497192382812},"width":1071,"sublayerTransform":[1,0,0,0,0,1,0,0,0,0,1,0,0,0,0,1],"contentsRect":{"y":0,"x":0,"width":1,"height":1},"opacity":1,"edgeAntialiasingMask":251658240,"height":201,"hidden":false,"anchorPoint":{"pointX":0.5,"pointY":0.5}},"layers":[{"animations":[],"initialState":{"affineTransform":[1,0,0,1,0,0],"masksToBounds":false,"rotation":0,"scale":1,"position":{"pointX":569.53376770019531,"pointY":-22.564971923828125},"width":1071,"sublayerTransform":[1,0,0,0,0,1,0,0,0,0,1,-0.00046677216622367974,0,0,0,1],"contentsRect":{"y":0,"x":0,"width":1,"height":1},"opacity":1,"edgeAntialiasingMask":251658240,"height":201,"hidden":false,"anchorPoint":{"pointX":0.53177756087786676,"pointY":-0.11226354190959266}},"layers":[{"animations":[],"layers":[],"texturedRectangle":{"singleTextureOpacity":1,"textXHeight":0.072716417910447764,"textBaseline":0.9699749872459108,"isBackgroundTexture":true,"isVerticalText":false,"textColor":[0.098039217293262482,0.098039217293262482,0.098039217293262482,1],"textureType":6},"initialState":{"affineTransform":[1,0,0,1,0,0],"masksToBounds":false,"rotation":0,"scale":1,"position":{"pointX":535.03376770019531,"pointY":111.93502807617188},"width":1071,"sublayerTransform":[1,0,0,0,0,1,0,0,0,0,1,0,0,0,0,1],"contentsRect":{"y":0,"x":0,"width":1,"height":1},"opacity":1,"edgeAntialiasingMask":0,"height":201,"hidden":false,"anchorPoint":{"pointX":0.5,"pointY":0.5}},"texture":"C1DFBD659D6C7908D9CDD0DC73CDF2C2"}]}]},{"animations":[],"initialState":{"affineTransform":[1,0,0,1,0,0],"masksToBounds":false,"rotation":0,"scale":1,"position":{"pointX":1124.4106398261183,"pointY":829.18346697455559},"width":501,"sublayerTransform":[1,0,0,0,0,1,0,0,0,0,1,0,0,0,0,1],"contentsRect":{"y":0,"x":0,"width":1,"height":1},"opacity":1,"edgeAntialiasingMask":251658240,"height":500,"hidden":false,"anchorPoint":{"pointX":0.5,"pointY":0.5}},"layers":[{"animations":[],"initialState":{"affineTransform":[1,0,0,1,0,0],"masksToBounds":false,"rotation":0,"scale":1,"position":{"pointX":-153.91063982611831,"pointY":-174.18346697455559},"width":501,"sublayerTransform":[1,0,0,0,0,1,0,0,0,0,1,-0.00046677216622367974,0,0,0,1],"contentsRect":{"y":0,"x":0,"width":1,"height":1},"opacity":1,"edgeAntialiasingMask":251658240,"height":500,"hidden":false,"anchorPoint":{"pointX":-0.30720686592039581,"pointY":-0.34836693394911117}},"layers":[{"animations":[],"layers":[],"texturedRectangle":{"singleTextureOpacity":1,"textXHeight":0,"shapePath":{"lineWidth":1,"flatness":0.59999999999999998,"lineCapStyle":0,"elements":[{"type":"MoveToPoint","points":[[422.05015960665264,172.65592882730198]]},{"type":"AddCurve","points":[[379.41667100338304,77.954102276295089],[268.08492822987137,35.744574446327874],[173.38310167886448,78.378063049597472]]},{"type":"AddCurve","points":[[78.681261214011329,121.0115579166935],[36.471747297890488,232.34329442637886],[79.105235901160086,327.04512097738552]]},{"type":"AddCurve","points":[[121.73873076825612,421.74696144223878],[233.0704533640951,463.95648162218617],[327.77229382894825,421.32298675509014]]},{"type":"AddCurve","points":[[422.47412037995514,378.68949815182054],[464.6836544737489,267.35776929215513],[422.05015960665264,172.65592882730198]]},{"type":"CloseSubpath"},{"type":"MoveToPoint","points":[[422.05015960665264,172.65592882730198]]}],"windingRule":0,"lineJoinStyle":0,"miterLimit":10},"isBackgroundTexture":true,"textBaseline":0,"isVerticalText":false,"textureType":5},"initialState":{"affineTransform":[1,0,0,1,0,0],"masksToBounds":false,"rotation":0,"scale":1,"position":{"pointX":248.5893601738818,"pointY":248.81653302544441},"width":501,"sublayerTransform":[1,0,0,0,0,1,0,0,0,0,1,0,0,0,0,1],"contentsRect":{"y":0,"x":0,"width":1,"height":1},"opacity":1,"edgeAntialiasingMask":0,"height":500,"hidden":false,"anchorPoint":{"pointX":0.5,"pointY":0.5}},"texture":"40E44A2A8C979B522C9F6AF8F9971FEB"}]}]},{"animations":[],"initialState":{"affineTransform":[1,0,0,1,0,0],"masksToBounds":false,"rotation":0,"scale":1,"position":{"pointX":423.94480895996094,"pointY":90.823539733886719},"width":513,"sublayerTransform":[1,0,0,0,0,1,0,0,0,0,1,0,0,0,0,1],"contentsRect":{"y":0,"x":0,"width":1,"height":1},"opacity":1,"edgeAntialiasingMask":251658240,"height":47,"hidden":false,"anchorPoint":{"pointX":0.5,"pointY":0.5}},"layers":[{"animations":[],"initialState":{"affineTransform":[1,0,0,1,0,0],"masksToBounds":false,"rotation":0,"scale":1,"position":{"pointX":552.55519104003906,"pointY":337.67646026611328},"width":513,"sublayerTransform":[1,0,0,0,0,1,0,0,0,0,1,-0.00046677216622367974,0,0,0,1],"contentsRect":{"y":0,"x":0,"width":1,"height":1},"opacity":1,"edgeAntialiasingMask":251658240,"height":47,"hidden":false,"anchorPoint":{"pointX":1.0771056355556317,"pointY":7.1846055375768785}},"layers":[{"animations":[],"layers":[],"texturedRectangle":{"singleTextureOpacity":1,"textXHeight":0.67912765957446797,"textBaseline":0.93454341305063127,"isBackgroundTexture":true,"isVerticalText":false,"textColor":[0,0,0,1],"textureType":6},"initialState":{"affineTransform":[1,0,0,1,0,0],"masksToBounds":false,"rotation":0,"scale":1,"position":{"pointX":260.05519104003906,"pointY":25.176460266113281},"width":513,"sublayerTransform":[1,0,0,0,0,1,0,0,0,0,1,0,0,0,0,1],"contentsRect":{"y":0,"x":0,"width":1,"height":1},"opacity":1,"edgeAntialiasingMask":0,"height":47,"hidden":false,"anchorPoint":{"pointX":0.5,"pointY":0.5}},"texture":"592D87926DE8EFDA616186EC5A2EF4D4"}]}]},{"animations":[],"initialState":{"affineTransform":[1,0,0,1,0,0],"masksToBounds":false,"rotation":0,"scale":1,"position":{"pointX":694.57368469238281,"pointY":268.21676635742188},"width":1076,"sublayerTransform":[1,0,0,0,0,1,0,0,0,0,1,0,0,0,0,1],"contentsRect":{"y":0,"x":0,"width":1,"height":1},"opacity":1,"edgeAntialiasingMask":251658240,"height":244,"hidden":false,"anchorPoint":{"pointX":0.5,"pointY":0.5}},"layers":[{"animations":[],"initialState":{"affineTransform":[1,0,0,1,0,0],"masksToBounds":false,"rotation":0,"scale":1,"position":{"pointX":563.42631530761719,"pointY":258.78323364257812},"width":1076,"sublayerTransform":[1,0,0,0,0,1,0,0,0,0,1,-0.00046677216622367974,0,0,0,1],"contentsRect":{"y":0,"x":0,"width":1,"height":1},"opacity":1,"edgeAntialiasingMask":251658240,"height":244,"hidden":false,"anchorPoint":{"pointX":0.52363040456098253,"pointY":1.0605870231253203}},"layers":[{"animations":[],"layers":[],"texturedRectangle":{"singleTextureOpacity":1,"textXHeight":0.059901639344262292,"textBaseline":0.97383920848369598,"isBackgroundTexture":true,"isVerticalText":false,"textColor":[0.098039217293262482,0.098039217293262482,0.098039217293262482,1],"textureType":6},"initialState":{"affineTransform":[1,0,0,1,0,0],"masksToBounds":false,"rotation":0,"scale":1,"position":{"pointX":537.42631530761719,"pointY":133.78323364257812},"width":1076,"sublayerTransform":[1,0,0,0,0,1,0,0,0,0,1,0,0,0,0,1],"contentsRect":{"y":0,"x":0,"width":1,"height":1},"opacity":1,"edgeAntialiasingMask":0,"height":244,"hidden":false,"anchorPoint":{"pointX":0.5,"pointY":0.5}},"texture":"D371801AE33A0681B1EC4A22B0EBAF90"}]}]},{"animations":[],"initialState":{"affineTransform":[1,0,0,1,0,0],"masksToBounds":false,"rotation":0,"scale":1,"position":{"pointX":1323.021240234375,"pointY":82.690155029296875},"width":77,"sublayerTransform":[1,0,0,0,0,1,0,0,0,0,1,0,0,0,0,1],"contentsRect":{"y":0,"x":0,"width":1,"height":1},"opacity":1,"edgeAntialiasingMask":251658240,"height":22,"hidden":false,"anchorPoint":{"pointX":0.5,"pointY":0.5}},"layers":[{"animations":[],"layers":[],"texturedRectangle":{"singleTextureOpacity":1,"textXHeight":0,"shapePath":{"lineWidth":1,"flatness":0.59999999999999998,"lineCapStyle":0,"elements":[{"type":"MoveToPoint","points":[[1.521240234375,1.690155029296875]]},{"type":"AddLine","points":[[75.999977111816406,1.690155029296875]]},{"type":"AddLine","points":[[75.999977111816406,20.309839248657227]]},{"type":"AddLine","points":[[1.521240234375,20.309839248657227]]},{"type":"AddLine","points":[[1.521240234375,1.690155029296875]]},{"type":"CloseSubpath"},{"type":"MoveToPoint","points":[[1.521240234375,1.690155029296875]]}],"windingRule":0,"lineJoinStyle":0,"miterLimit":10},"isBackgroundTexture":true,"textBaseline":0,"isVerticalText":false,"textureType":5},"initialState":{"affineTransform":[1,0,0,1,0,0],"masksToBounds":false,"rotation":0,"scale":1,"position":{"pointX":36.978759765625,"pointY":9.309844970703125},"width":77,"sublayerTransform":[1,0,0,0,0,1,0,0,0,0,1,0,0,0,0,1],"contentsRect":{"y":0,"x":0,"width":1,"height":1},"opacity":1,"edgeAntialiasingMask":0,"height":22,"hidden":true,"anchorPoint":{"pointX":0.5,"pointY":0.5}},"texture":"A5CB58C0EC26082A6A1D79A500ACD787"}]},{"animations":[],"initialState":{"affineTransform":[1,0,0,1,0,0],"masksToBounds":false,"rotation":0,"scale":1,"position":{"pointX":409.00000762939453,"pointY":34.189841270446777},"width":656,"sublayerTransform":[1,0,0,0,0,1,0,0,0,0,1,0,0,0,0,1],"contentsRect":{"y":0,"x":0,"width":1,"height":1},"opacity":1,"edgeAntialiasingMask":251658240,"height":47,"hidden":false,"anchorPoint":{"pointX":0.5,"pointY":0.5}},"layers":[{"animations":[],"layers":[],"texturedRectangle":{"singleTextureOpacity":1,"textXHeight":0.67912765957446797,"textBaseline":0.93808175021029538,"isBackgroundTexture":true,"isVerticalText":false,"textColor":[0.098039217293262482,0.098039217293262482,0.098039217293262482,1],"textureType":6},"initialState":{"affineTransform":[1,0,0,1,0,0],"masksToBounds":false,"rotation":0,"scale":1,"position":{"pointX":330.99999237060547,"pointY":45.810158729553223},"width":656,"sublayerTransform":[1,0,0,0,0,1,0,0,0,0,1,0,0,0,0,1],"contentsRect":{"y":0,"x":0,"width":1,"height":1},"opacity":1,"edgeAntialiasingMask":0,"height":47,"hidden":true,"anchorPoint":{"pointX":0.5,"pointY":0.5}},"texture":"5925DF463A6EE8451015429E757C9BE9"}]},{"animations":[],"initialState":{"affineTransform":[1,0,0,1,0,0],"masksToBounds":false,"rotation":0,"scale":1,"position":{"pointX":413.60582733154297,"pointY":130.52897644042969},"width":594,"sublayerTransform":[1,0,0,0,0,1,0,0,0,0,1,0,0,0,0,1],"contentsRect":{"y":0,"x":0,"width":1,"height":1},"opacity":1,"edgeAntialiasingMask":251658240,"height":34,"hidden":false,"anchorPoint":{"pointX":0.5,"pointY":0.5}},"layers":[{"animations":[],"layers":[],"texturedRectangle":{"singleTextureOpacity":1,"textXHeight":0.52508823529411774,"textBaseline":0.78026402873151446,"isBackgroundTexture":true,"isVerticalText":false,"textColor":[0.098039217293262482,0.098039217293262482,0.098039217293262482,1],"textureType":6},"initialState":{"affineTransform":[1,0,0,1,0,0],"masksToBounds":false,"rotation":0,"scale":1,"position":{"pointX":296.39417266845703,"pointY":26.471023559570312},"width":594,"sublayerTransform":[1,0,0,0,0,1,0,0,0,0,1,0,0,0,0,1],"contentsRect":{"y":0,"x":0,"width":1,"height":1},"opacity":1,"edgeAntialiasingMask":0,"height":34,"hidden":true,"anchorPoint":{"pointX":0.5,"pointY":0.5}},"texture":"3ED2370E1D55959704E6F5A81484B4D9"}]},{"animations":[],"initialState":{"affineTransform":[1,0,0,1,0,0],"masksToBounds":false,"rotation":0,"scale":1,"position":{"pointX":661.10584259033203,"pointY":239.0108642578125},"width":1089,"sublayerTransform":[1,0,0,0,0,1,0,0,0,0,1,0,0,0,0,1],"contentsRect":{"y":0,"x":0,"width":1,"height":1},"opacity":1,"edgeAntialiasingMask":251658240,"height":171,"hidden":false,"anchorPoint":{"pointX":0.5,"pointY":0.5}},"layers":[{"animations":[],"layers":[],"texturedRectangle":{"singleTextureOpacity":1,"textXHeight":0.081473684210526323,"textBaseline":1.2111746473619116,"isBackgroundTexture":true,"isVerticalText":false,"textColor":[0.098039217293262482,0.098039217293262482,0.098039217293262482,1],"textureType":6},"initialState":{"affineTransform":[1,0,0,1,0,0],"masksToBounds":false,"rotation":0,"scale":1,"position":{"pointX":543.89415740966797,"pointY":92.9891357421875},"width":1089,"sublayerTransform":[1,0,0,0,0,1,0,0,0,0,1,0,0,0,0,1],"contentsRect":{"y":0,"x":0,"width":1,"height":1},"opacity":1,"edgeAntialiasingMask":0,"height":171,"hidden":true,"anchorPoint":{"pointX":0.5,"pointY":0.5}},"texture":"765E2EA5592FB78B20F4EC16AC7FD7A0"}]},{"animations":[],"initialState":{"affineTransform":[1,0,0,1,0,0],"masksToBounds":false,"rotation":0,"scale":1,"position":{"pointX":63.991968154907227,"pointY":138.88558959960938},"width":67,"sublayerTransform":[1,0,0,0,0,1,0,0,0,0,1,0,0,0,0,1],"contentsRect":{"y":0,"x":0,"width":1,"height":1},"opacity":1,"edgeAntialiasingMask":251658240,"height":67,"hidden":false,"anchorPoint":{"pointX":0.5,"pointY":0.5}},"layers":[{"animations":[],"layers":[],"texturedRectangle":{"isBackgroundTexture":true,"singleTextureOpacity":1,"textureType":5,"textBaseline":0,"textXHeight":0,"isVerticalText":false},"initialState":{"affineTransform":[1,0,0,1,0,0],"masksToBounds":false,"rotation":0,"scale":1,"position":{"pointX":32.008031845092773,"pointY":32.114410400390625},"width":67,"sublayerTransform":[1,0,0,0,0,1,0,0,0,0,1,0,0,0,0,1],"contentsRect":{"y":0,"x":0,"width":1,"height":1},"opacity":1,"edgeAntialiasingMask":0,"height":67,"hidden":true,"anchorPoint":{"pointX":0.5,"pointY":0.5}},"texture":"AD6454C95626FBA9C44ECC02468B867F"}]},{"animations":[],"initialState":{"affineTransform":[1,0,0,1,0,0],"masksToBounds":false,"rotation":0,"scale":1,"position":{"pointX":364.10587310791016,"pointY":345.32330322265625},"width":495,"sublayerTransform":[1,0,0,0,0,1,0,0,0,0,1,0,0,0,0,1],"contentsRect":{"y":0,"x":0,"width":1,"height":1},"opacity":1,"edgeAntialiasingMask":251658240,"height":72,"hidden":false,"anchorPoint":{"pointX":0.5,"pointY":0.5}},"layers":[{"animations":[],"layers":[],"texturedRectangle":{"singleTextureOpacity":1,"textXHeight":0.24795833333333336,"textBaseline":1.6156014410985842,"isBackgroundTexture":true,"isVerticalText":false,"textColor":[0.098039217293262482,0.098039217293262482,0.098039217293262482,1],"textureType":6},"initialState":{"affineTransform":[1,0,0,1,0,0],"masksToBounds":false,"rotation":0,"scale":1,"position":{"pointX":246.89412689208984,"pointY":45.67669677734375},"width":495,"sublayerTransform":[1,0,0,0,0,1,0,0,0,0,1,0,0,0,0,1],"contentsRect":{"y":0,"x":0,"width":1,"height":1},"opacity":1,"edgeAntialiasingMask":0,"height":72,"hidden":true,"anchorPoint":{"pointX":0.5,"pointY":0.5}},"texture":"1FA82269F68C3079E3607ACE6DA313F7"}]},{"animations":[],"initialState":{"affineTransform":[1,0,0,1,0,0],"masksToBounds":false,"rotation":0,"scale":1,"position":{"pointX":66.491968154907227,"pointY":343.65692138671875},"width":72,"sublayerTransform":[1,0,0,0,0,1,0,0,0,0,1,0,0,0,0,1],"contentsRect":{"y":0,"x":0,"width":1,"height":1},"opacity":1,"edgeAntialiasingMask":251658240,"height":76,"hidden":false,"anchorPoint":{"pointX":0.5,"pointY":0.5}},"layers":[{"animations":[],"layers":[],"texturedRectangle":{"isBackgroundTexture":true,"singleTextureOpacity":1,"textureType":5,"textBaseline":0,"textXHeight":0,"isVerticalText":false},"initialState":{"affineTransform":[1,0,0,1,0,0],"masksToBounds":false,"rotation":0,"scale":1,"position":{"pointX":34.508031845092773,"pointY":36.34307861328125},"width":72,"sublayerTransform":[1,0,0,0,0,1,0,0,0,0,1,0,0,0,0,1],"contentsRect":{"y":0,"x":0,"width":1,"height":1},"opacity":1,"edgeAntialiasingMask":0,"height":76,"hidden":true,"anchorPoint":{"pointX":0.5,"pointY":0.5}},"texture":"713FBE56E9B67C4EE271793F37875EE2"}]},{"animations":[],"initialState":{"affineTransform":[1,0,0,1,0,0],"masksToBounds":false,"rotation":0,"scale":1,"position":{"pointX":632.10582733154297,"pointY":435.0279541015625},"width":1031,"sublayerTransform":[1,0,0,0,0,1,0,0,0,0,1,0,0,0,0,1],"contentsRect":{"y":0,"x":0,"width":1,"height":1},"opacity":1,"edgeAntialiasingMask":251658240,"height":170,"hidden":false,"anchorPoint":{"pointX":0.5,"pointY":0.5}},"layers":[{"animations":[],"layers":[],"texturedRectangle":{"singleTextureOpacity":1,"textXHeight":0.08195294117647059,"textBaseline":1.2154585561331581,"isBackgroundTexture":true,"isVerticalText":false,"textColor":[0.098039217293262482,0.098039217293262482,0.098039217293262482,1],"textureType":6},"initialState":{"affineTransform":[1,0,0,1,0,0],"masksToBounds":false,"rotation":0,"scale":1,"position":{"pointX":514.89417266845703,"pointY":92.9720458984375},"width":1031,"sublayerTransform":[1,0,0,0,0,1,0,0,0,0,1,0,0,0,0,1],"contentsRect":{"y":0,"x":0,"width":1,"height":1},"opacity":1,"edgeAntialiasingMask":0,"height":170,"hidden":true,"anchorPoint":{"pointX":0.5,"pointY":0.5}},"texture":"4C0554448575FCE60EE0460D8D53B606"}]},{"animations":[],"initialState":{"affineTransform":[1,0,0,1,0,0],"masksToBounds":false,"rotation":0,"scale":1,"position":{"pointX":397.10581970214844,"pointY":561.62860107421875},"width":561,"sublayerTransform":[1,0,0,0,0,1,0,0,0,0,1,0,0,0,0,1],"contentsRect":{"y":0,"x":0,"width":1,"height":1},"opacity":1,"edgeAntialiasingMask":251658240,"height":34,"hidden":false,"anchorPoint":{"pointX":0.5,"pointY":0.5}},"layers":[{"animations":[],"layers":[],"texturedRectangle":{"singleTextureOpacity":1,"textXHeight":0.52508823529411774,"textBaseline":2.1067235767841339,"isBackgroundTexture":true,"isVerticalText":false,"textColor":[0.098039217293262482,0.098039217293262482,0.098039217293262482,1],"textureType":6},"initialState":{"affineTransform":[1,0,0,1,0,0],"masksToBounds":false,"rotation":0,"scale":1,"position":{"pointX":280.89418029785156,"pointY":26.37139892578125},"width":561,"sublayerTransform":[1,0,0,0,0,1,0,0,0,0,1,0,0,0,0,1],"contentsRect":{"y":0,"x":0,"width":1,"height":1},"opacity":1,"edgeAntialiasingMask":0,"height":34,"hidden":true,"anchorPoint":{"pointX":0.5,"pointY":0.5}},"texture":"F1F1BD7DF227BF49CD6A9F7B48A28CFE"}]},{"animations":[],"initialState":{"affineTransform":[1,0,0,1,0,0],"masksToBounds":false,"rotation":0,"scale":1,"position":{"pointX":66.491968154907227,"pointY":577.67401123046875},"width":72,"sublayerTransform":[1,0,0,0,0,1,0,0,0,0,1,0,0,0,0,1],"contentsRect":{"y":0,"x":0,"width":1,"height":1},"opacity":1,"edgeAntialiasingMask":251658240,"height":76,"hidden":false,"anchorPoint":{"pointX":0.5,"pointY":0.5}},"layers":[{"animations":[],"layers":[],"texturedRectangle":{"isBackgroundTexture":true,"singleTextureOpacity":1,"textureType":5,"textBaseline":0,"textXHeight":0,"isVerticalText":false},"initialState":{"affineTransform":[1,0,0,1,0,0],"masksToBounds":false,"rotation":0,"scale":1,"position":{"pointX":34.508031845092773,"pointY":36.32598876953125},"width":72,"sublayerTransform":[1,0,0,0,0,1,0,0,0,0,1,0,0,0,0,1],"contentsRect":{"y":0,"x":0,"width":1,"height":1},"opacity":1,"edgeAntialiasingMask":0,"height":76,"hidden":true,"anchorPoint":{"pointX":0.5,"pointY":0.5}},"texture":"5CF8AE5C26095294EC1BE0FB30046E9E"}]},{"animations":[],"initialState":{"affineTransform":[1,0,0,1,0,0],"masksToBounds":false,"rotation":0,"scale":1,"position":{"pointX":656.10581970214844,"pointY":683.79833984375},"width":1079,"sublayerTransform":[1,0,0,0,0,1,0,0,0,0,1,0,0,0,0,1],"contentsRect":{"y":0,"x":0,"width":1,"height":1},"opacity":1,"edgeAntialiasingMask":251658240,"height":177,"hidden":false,"anchorPoint":{"pointX":0.5,"pointY":0.5}},"layers":[{"animations":[],"layers":[],"texturedRectangle":{"singleTextureOpacity":1,"textXHeight":0.078711864406779658,"textBaseline":0.95987762872782134,"isBackgroundTexture":true,"isVerticalText":false,"textColor":[0.098039217293262482,0.098039217293262482,0.098039217293262482,1],"textureType":6},"initialState":{"affineTransform":[1,0,0,1,0,0],"masksToBounds":false,"rotation":0,"scale":1,"position":{"pointX":538.89418029785156,"pointY":96.20166015625},"width":1079,"sublayerTransform":[1,0,0,0,0,1,0,0,0,0,1,0,0,0,0,1],"contentsRect":{"y":0,"x":0,"width":1,"height":1},"opacity":1,"edgeAntialiasingMask":0,"height":177,"hidden":true,"anchorPoint":{"pointX":0.5,"pointY":0.5}},"texture":"99B08C3706E8C4B69AC19EB1564417ED"}]},{"animations":[],"initialState":{"affineTransform":[1,0,0,1,0,0],"masksToBounds":false,"rotation":0,"scale":1,"position":{"pointX":-481.39499304059063,"pointY":673.58799340960445},"width":1221,"sublayerTransform":[1,0,0,0,0,1,0,0,0,0,1,0,0,0,0,1],"contentsRect":{"y":0,"x":0,"width":1,"height":1},"opacity":1,"edgeAntialiasingMask":251658240,"height":1221,"hidden":false,"anchorPoint":{"pointX":0.5,"pointY":0.5}},"layers":[{"animations":[],"layers":[],"texturedRectangle":{"singleTextureOpacity":1,"textXHeight":0,"shapePath":{"lineWidth":1,"flatness":0.59999999999999998,"lineCapStyle":0,"elements":[{"type":"MoveToPoint","points":[[414.31708070820491,224.19712085482263]]},{"type":"AddCurve","points":[[201.14011738237286,332.38290143547692],[116.02835382397313,592.89763382240835],[224.21413440462743,806.07459714824051]]},{"type":"AddCurve","points":[[332.39990807990262,1019.251546867222],[592.91464737221327,1104.3633240324723],[806.09161069804543,996.17754345181788]]},{"type":"AddCurve","points":[[1019.2685604170268,887.99176977654281],[1104.380330676898,627.47701687738163],[996.1945570016228,414.30006715840011]]},{"type":"AddCurve","points":[[888.0087764209685,201.12310383256801],[627.49403042718643,116.01134717954744],[414.31708070820491,224.19712085482263]]},{"type":"CloseSubpath"},{"type":"MoveToPoint","points":[[414.31708070820491,224.19712085482263]]}],"windingRule":0,"lineJoinStyle":0,"miterLimit":10},"isBackgroundTexture":true,"textBaseline":0,"isVerticalText":false,"textureType":5},"initialState":{"affineTransform":[1,0,0,1,0,0],"masksToBounds":false,"rotation":0,"scale":1,"position":{"pointX":609.39499304059063,"pointY":609.41200659039555},"width":1221,"sublayerTransform":[1,0,0,0,0,1,0,0,0,0,1,0,0,0,0,1],"contentsRect":{"y":0,"x":0,"width":1,"height":1},"opacity":1,"edgeAntialiasingMask":0,"height":1221,"hidden":true,"anchorPoint":{"pointX":0.5,"pointY":0.5}},"texture":"35BEB27BCFD2A0671D05F54DF7529643"}]},{"animations":[],"initialState":{"affineTransform":[1,0,0,1,0,0],"masksToBounds":false,"rotation":0,"scale":1,"position":{"pointX":139.08324924155897,"pointY":802.25564787777023},"width":1759,"sublayerTransform":[1,0,0,0,0,1,0,0,0,0,1,0,0,0,0,1],"contentsRect":{"y":0,"x":0,"width":1,"height":1},"opacity":1,"edgeAntialiasingMask":251658240,"height":1769,"hidden":false,"anchorPoint":{"pointX":0.5,"pointY":0.5}},"layers":[{"animations":[],"layers":[],"texturedRectangle":{"singleTextureOpacity":1,"textXHeight":0,"shapePath":{"lineWidth":1,"flatness":0.59999999999999998,"lineCapStyle":0,"elements":[{"type":"MoveToPoint","points":[[411.88395517272335,519.77980538225074]]},{"type":"AddCurve","points":[[200.97774738712678,790.17965173825337],[239.32959639322678,1172.6506465620987],[497.54442190203844,1374.0527937008337]]},{"type":"AddCurve","points":[[755.75927147427558,1575.4549596085358],[1136.0561860794678,1519.5212181052348],[1346.9623938650643,1249.1213717492319]]},{"type":"AddCurve","points":[[1557.8686016506608,978.72152539322929],[1519.5182435982529,596.25045499155021],[1261.3033940260161,394.84828908384827]]},{"type":"AddCurve","points":[[1003.0885685172043,193.44614194511325],[622.79016295831991,249.379959026248],[411.88395517272335,519.77980538225074]]},{"type":"CloseSubpath"},{"type":"MoveToPoint","points":[[411.88395517272335,519.77980538225074]]}],"windingRule":0,"lineJoinStyle":0,"miterLimit":10},"isBackgroundTexture":true,"textBaseline":0,"isVerticalText":false,"textureType":5},"initialState":{"affineTransform":[1,0,0,1,0,0],"masksToBounds":false,"rotation":0,"scale":1,"position":{"pointX":877.91675075844103,"pointY":882.74435212222977},"width":1759,"sublayerTransform":[1,0,0,0,0,1,0,0,0,0,1,0,0,0,0,1],"contentsRect":{"y":0,"x":0,"width":1,"height":1},"opacity":1,"edgeAntialiasingMask":0,"height":1769,"hidden":true,"anchorPoint":{"pointX":0.5,"pointY":0.5}},"texture":"7417B7E31B0B5A22D6C7FCE2448F6A8B"}]}]}}]}